Workbook
Name Company_Name: FSM!$D$5
Name Company_Name: #REF!
Name Hist_Yr: FSM!#REF!
Name Hist_Yr: #REF!
Name IQ_CH: 110000
Name IQ_CQ: 5000
Name IQ_CY: 10000
Name IQ_DAILY: 500000
Name IQ_FH: 100000
Name IQ_FQ: 500
Name IQ_FY: 1000
Name IQ_LTM: 2000
Name IQ_MONTH: 15000
Name IQ_NTM: 6000
Name IQ_WEEK: 50000
Name IQ_YTD: 3000

Sheet FSM
C2: =Company_Name&" - Financial Statement Model" -> Gourmet Egypt - Financial Statement Model
C3: All amounts are shown in EGP, except per-share data, ratios, and shares outstanding
C5: Company Name | D5: Gourmet Egypt
C6: Ticker | D6: GOUR.CA
C7: Latest Closing Share Price | D7: 17.03
C8: Latest Closing Share Price Date | D8: 46274
C9: Last Historical Year | D9: 46022
C10: Shares outstanding | D10: 400000000
C12: INCOME STATEMENT
C13: Fiscal year | D13: =E13-1 -> 2023 | E13: =F13-1 -> 2024 | F13: =YEAR(D9) -> 2025 | G13: =F13+1 -> 2026 | H13: =G13+1 -> 2027 | I13: =H13+1 -> 2028 | J13: =I13+1 -> 2029 | K13: =J13+1 -> 2030
C14: Fiscal year end date | D14: =EOMONTH(E14,-12) -> 45291 | E14: =EOMONTH(F14,-12) -> 45657 | F14: =D9 -> 46022 | G14: =EOMONTH(F14,12) -> 46387 | H14: =EOMONTH(G14,12) -> 46752 | I14: =EOMONTH(H14,12) -> 47118 | J14: =EOMONTH(I14,12) -> 47483 | K14: =EOMONTH(J14,12) -> 47848
C16: Gross Revenue | D16: 1461003005 | E16: 2117799758 | F16: 2877655973 | G16: =G185 -> 3.5122413e+09 | H16: =H185 -> 4.1456704e+09 | I16: =I185 -> 4.7685376e+09 | J16: =J185 -> 5.3415609e+09 | K16: =K185 -> 5.8763698e+09
C17: Cost of Goods Sold (COGS) | D17: -988835102 | E17: -1426005686 | F17: -1923541960 | G17: =-G16*(1-G39) -> -2.3632735e+09 | H17: =-H16*(1-H39) -> -2.7894875e+09 | I17: =-I16*(1-I39) -> -3.2085947e+09 | J17: =-J16*(1-J39) -> -3.5941635e+09 | K17: =-K16*(1-K39) -> -3.9540191e+09
C18: Gross Profit | D18: =SUM(D16:D17) -> 472167903 | E18: =SUM(E16:E17) -> 691794072 | F18: =SUM(F16:F17) -> 954114013 | G18: =SUM(G16:G17) -> 1.1489678e+09 | H18: =SUM(H16:H17) -> 1.3561829e+09 | I18: =SUM(I16:I17) -> 1.559943e+09 | J18: =SUM(J16:J17) -> 1.7473974e+09 | K18: =SUM(K16:K17) -> 1.9223507e+09
C19: Total Cash Operating Expenses (OpEx) | D19: =D57 -> -312854249 | E19: =E57 -> -405834952 | F19: =F57 -> -592354956 | G19: =G57 -> -6.9158878e+08 | H19: =H57 -> -8.1556945e+08 | I19: =I57 -> -9.3748286e+08 | J19: =J57 -> -1.0496403e+09 | K19: =K57 -> -1.1543181e+09
C20: EBITDA | D20: =SUM(D18:D19) -> 159313654 | E20: =SUM(E18:E19) -> 285959120 | F20: =SUM(F18:F19) -> 361759057 | G20: =SUM(G18:G19) -> 4.5737901e+08 | H20: =SUM(H18:H19) -> 5.4061349e+08 | I20: =SUM(I18:I19) -> 6.224601e+08 | J20: =SUM(J18:J19) -> 6.9775707e+08 | K20: =SUM(K18:K19) -> 7.6803256e+08
C21: Depreciation of Fixed Assets (PPE) | D21: -45088086 | E21: -43207268 | F21: -41355878 | G21: =-G164 -> -35411770 | H21: =-H164 -> -35348965 | I21: =-I164 -> -45672897 | J21: =-J164 -> -56459890 | K21: =-K164 -> -67393060
C22: Amortization of Intangible Assets | D22: -4505081 | E22: -7108381 | F22: -6938280 | G22: =G301 -> -7000000 | H22: =H301 -> -5000000 | I22: =I301 -> -4000000 | J22: =J301 -> -3000000 | K22: =K301 -> -2000000
C23: Amortization of Right-of-Use Assets | D23: -33206271 | E23: -36035425 | F23: -36334900 | G23: =G288 -> -44347531 | H23: =H288 -> -52345562 | I23: =I288 -> -60210233 | J23: =J288 -> -67445546 | K23: =K288 -> -74198345
C24: Total D&A | D24: =SUM(D21:D23) -> -82799438 | E24: =SUM(E21:E23) -> -86351074 | F24: =SUM(F21:F23) -> -84629058 | G24: =SUM(G21:G23) -> -86759301 | H24: =SUM(H21:H23) -> -92694527 | I24: =SUM(I21:I23) -> -1.0988313e+08 | J24: =SUM(J21:J23) -> -1.2690544e+08 | K24: =SUM(K21:K23) -> -1.4359141e+08
C25: Operating Profit (EBIT) | D25: =D20+D24 -> 76514216 | E25: =E20+E24 -> 199608046 | F25: =F20+F24 -> 277129999 | G25: =G20+G24 -> 3.7061971e+08 | H25: =H20+H24 -> 4.4791896e+08 | I25: =I20+I24 -> 5.1257697e+08 | J25: =J20+J24 -> 5.7085163e+08 | K25: =K20+K24 -> 6.2444116e+08
C26: Finance expense | D26: -47950964 | E26: -55620920 | F26: -37780877 | G26: =G241 -> -40228350 | H26: =H241 -> -41822344 | I26: =I241 -> -45435245 | J26: =J241 -> -50173503 | K26: =K241 -> -55196986
C27: Other Income / (Expenses) & Capital Gains | D27: -435610 | E27: 8483341 | F27: 36040096 | G27: =G242 -> 42840526 | H27: =H242 -> 43720738 | I27: =I242 -> 49860748 | J27: =J242 -> 55317613 | K27: =K242 -> 69154501
C28: Profit / (Loss) Before Tax (EBT) | D28: =SUM(D25:D27) -> 28127642 | E28: =SUM(E25:E27) -> 152470467 | F28: =SUM(F25:F27) -> 275389218 | G28: =SUM(G25:G27) -> 3.7323189e+08 | H28: =SUM(H25:H27) -> 4.4981736e+08 | I28: =SUM(I25:I27) -> 5.1700248e+08 | J28: =SUM(J25:J27) -> 5.7599574e+08 | K28: =SUM(K25:K27) -> 6.3839868e+08
C29: Income Tax Expense (Current) | D29: 0 | E29: -22336568 | F29: -69211808 | G29: =G28*-G40 -> -83977175 | H29: =H28*-H40 -> -1.0120891e+08 | I29: =I28*-I40 -> -1.1632556e+08 | J29: =J28*-J40 -> -1.2959904e+08 | K29: =K28*-K40 -> -1.436397e+08
C30: Deferred Tax (Expense) / Benefit | D30: 3617966 | E30: 4907885 | F30: 5035222 | G30: 0 | H30: =G30 -> 0 | I30: =H30 -> 0 | J30: =I30 -> 0 | K30: =J30 -> 0
C31: Net Profit / (Loss) for the Year | D31: =SUM(D28:D30) -> 31745608 | E31: =SUM(E28:E30) -> 135041784 | F31: =SUM(F28:F30) -> 211212632 | G31: =SUM(G28:G30) -> 2.8925471e+08 | H31: =SUM(H28:H30) -> 3.4860845e+08 | I31: =SUM(I28:I30) -> 4.0067692e+08 | J31: =SUM(J28:J30) -> 4.463967e+08 | K31: =SUM(K28:K30) -> 4.9475897e+08
C32: Equity Holders of the Parent Company | D32: =D31-D33 -> 31745161 | E32: =E31-E33 -> 135031718 | F32: =F31-F33 -> 211202869 | G32: =G31-G33 -> 2.8924134e+08 | H32: =H31-H33 -> 3.4859234e+08 | I32: =I31-I33 -> 4.006584e+08 | J32: =J31-J33 -> 4.4637607e+08 | K32: =K31-K33 -> 4.947361e+08
C33: Non-Controlling Interest (NCI) | D33: 447 | E33: 10066 | F33: 9763 | G33: =G257 -> 13370.383 | H33: =H257 -> 16113.924 | I33: =I257 -> 18520.714 | J33: =J257 -> 20634.045 | K33: =K257 -> 22869.522
C35: Normalised EBITDA | D35: =D20-ABS(D49+D50+D51+D52+D56) -> 154063791 | E35: =E20-ABS(E49+E50+E51+E52+E56) -> 278963899 | F35: =F20-ABS(F49+F50+F51+F52+F56) -> 333679968 | G35: =G20-ABS(G49+G50+G51+G52+G56) -> 4.5737901e+08 | H35: =H20-ABS(H49+H50+H51+H52+H56) -> 5.4061349e+08 | I35: =I20-ABS(I49+I50+I51+I52+I56) -> 6.224601e+08 | J35: =J20-ABS(J49+J50+J51+J52+J56) -> 6.9775707e+08 | K35: =K20-ABS(K49+K50+K51+K52+K56) -> 7.6803256e+08
C37: Growth Rates & Margins
C38: Revenue growth | D38: =D16/1098037388-1 -> 0.33055852 | E38: =E16/D16-1 -> 0.44955195 | F38: =F16/E16-1 -> 0.35879512 | G38: =G16/F16-1 -> 0.22052162 | H38: =H16/G16-1 -> 0.18034897 | I38: =I16/H16-1 -> 0.15024523 | J38: =J16/I16-1 -> 0.1201675 | K38: =K16/J16-1 -> 0.10012223
C39: Gross Margin % of Revenue | D39: =D18/D16 -> 0.32318065 | E39: =E18/E16 -> 0.32665698 | F39: =F18/F16 -> 0.33155944 | G39: =AVERAGE(D39:F39) -> 0.32713236 | H39: =G39 -> 0.32713236 | I39: =H39 -> 0.32713236 | J39: =I39 -> 0.32713236 | K39: =J39 -> 0.32713236
C40: Tax rate | E40: =-SUM(E29:E30)/E28 -> 0.11430858 | F40: =-SUM(F29:F30)/F28 -> 0.23303957 | G40: 0.225 | H40: =G40 -> 0.225 | I40: =H40 -> 0.225 | J40: =I40 -> 0.225 | K40: =J40 -> 0.225
C41: Tax payable as % of annual charge | G41: 0.25 | H41: =G41 -> 0.25 | I41: =H41 -> 0.25 | J41: =I41 -> 0.25 | K41: =J41 -> 0.25
C43: OpEx Schedule
C44: Fiscal year | D44: =D$13 -> 2023 | E44: =E$13 -> 2024 | F44: =F$13 -> 2025 | G44: =G$13 -> 2026 | H44: =H$13 -> 2027 | I44: =I$13 -> 2028 | J44: =J$13 -> 2029 | K44: =K$13 -> 2030
C45: Fiscal year end date | D45: =D$14 -> 45291 | E45: =E$14 -> 45657 | F45: =F$14 -> 46022 | G45: =G$14 -> 46387 | H45: =H$14 -> 46752 | I45: =I$14 -> 47118 | J45: =J$14 -> 47483 | K45: =K$14 -> 47848
C47: Selling and Marketing Expenses | D47: -198930816 | E47: -277108013 | F47: -380179028 | G47: =-G$16*G59 -> -4.6727058e+08 | H47: =-H$16*H59 -> -5.5154235e+08 | I47: =-I$16*I59 -> -6.3440895e+08 | J47: =-J$16*J59 -> -7.1064429e+08 | K47: =-K$16*K59 -> -7.8179558e+08
C48: General and Administrative Expenses | D48: -100840540 | E48: -118109354 | F48: -178280004 | G48: =-G$16*G60 -> -2.1863057e+08 | H48: =-H$16*H60 -> -2.5806037e+08 | I48: =-I$16*I60 -> -2.9683271e+08 | J48: =-J$16*J60 -> -3.3250235e+08 | K48: =-K$16*K60 -> -3.6579323e+08
C49: Provisions Formed (other than depreciation) | D49: -8029570 | E49: -6779710 | F49: -27973094 | G49: 0 | H49: =G49 -> 0 | I49: =H49 -> 0 | J49: =I49 -> 0 | K49: =J49 -> 0
C50: Provisions No Longer Required | D50: 2955281 | E50: 29580 | F50: 0 | G50: =F50 -> 0 | H50: =G50 -> 0 | I50: =H50 -> 0 | J50: =I50 -> 0 | K50: =J50 -> 0
C51: Inventory Write-down (ECL / Slow Moving) | D51: 0 | E51: -510405 | F51: -253835 | G51: 0 | H51: =G51 -> 0 | I51: =H51 -> 0 | J51: =I51 -> 0 | K51: =J51 -> 0
C52: Reversal of Inventory Write-down | D52: 90349 | E52: 0 | F52: 425517 | G52: 0 | H52: =G52 -> 0 | I52: =H52 -> 0 | J52: =I52 -> 0 | K52: =J52 -> 0
C53: Impairment of Assets Held for Sale | D53: -2268481 | E53: 0 | F53: 0 | G53: 0 | H53: =G53 -> 0 | I53: =H53 -> 0 | J53: =I53 -> 0 | K53: =J53 -> 0
C54: Board Remuneration and Allowances | D54: -4500000 | E54: -3600000 | F54: -4140000 | G54: =F54 -> -4140000 | H54: =G54 -> -4140000 | I54: =H54 -> -4140000 | J54: =I54 -> -4140000 | K54: =J54 -> -4140000
C55: Expected Credit Loss (Trade & Other Debtors) | D55: -1064549 | E55: -22364 | F55: -1676835 | G55: =-G$16*G61 -> -1547623.8 | H55: =-H$16*H61 -> -1826736.1 | I55: =-I$16*I61 -> -2101194.5 | J55: =-J$16*J61 -> -2353689.8 | K55: =-K$16*K61 -> -2589346.4
C56: Net Foreign Exchange Gains / (Losses) | D56: -265923 | E56: 265314 | F56: -277677 | G56: 0 | H56: =G56 -> 0 | I56: =H56 -> 0 | J56: =I56 -> 0 | K56: =J56 -> 0
C57: Total Cash Operating Expenses (OpEx) | D57: =SUM(D47:D56) -> -312854249 | E57: =SUM(E47:E56) -> -405834952 | F57: =SUM(F47:F56) -> -592354956 | G57: =SUM(G47:G56) -> -6.9158878e+08 | H57: =SUM(H47:H56) -> -8.1556945e+08 | I57: =SUM(I47:I56) -> -9.3748286e+08 | J57: =SUM(J47:J56) -> -1.0496403e+09 | K57: =SUM(K47:K56) -> -1.1543181e+09
C59: =C47&" % of revenue" -> Selling and Marketing Expenses % of revenue | D59: =-D47/D$16 -> 0.13616044 | E59: =-E47/E$16 -> 0.13084713 | F59: =-F47/F$16 -> 0.13211413 | G59: =AVERAGE(D59:F59) -> 0.13304057 | H59: =G59 -> 0.13304057 | I59: =H59 -> 0.13304057 | J59: =I59 -> 0.13304057 | K59: =J59 -> 0.13304057
C60: =C48&" % of revenue" -> General and Administrative Expenses % of revenue | D60: =-D48/D$16 -> 0.069021446 | E60: =-E48/E$16 -> 0.05576984 | F60: =-F48/F$16 -> 0.061953203 | G60: =AVERAGE(D60:F60) -> 0.062248163 | H60: =G60 -> 0.062248163 | I60: =H60 -> 0.062248163 | J60: =I60 -> 0.062248163 | K60: =J60 -> 0.062248163
C61: =C55&" % of revenue" -> Expected Credit Loss (Trade & Other Debtors) % of revenue | D61: =-D55/D16 -> 0.00072864258 | E61: =-E55/E16 -> 1.0560016e-05 | F61: =-F55/F16 -> 0.00058270864 | G61: =AVERAGE(D61:F61) -> 0.00044063708 | H61: =G61 -> 0.00044063708 | I61: =H61 -> 0.00044063708 | J61: =I61 -> 0.00044063708 | K61: =J61 -> 0.00044063708
C63: BALANCE SHEET
C64: Fiscal year | D64: =D$13 -> 2023 | E64: =E$13 -> 2024 | F64: =F$13 -> 2025 | G64: =G$13 -> 2026 | H64: =H$13 -> 2027 | I64: =I$13 -> 2028 | J64: =J$13 -> 2029 | K64: =K$13 -> 2030
C65: Fiscal year end date | D65: =D$14 -> 45291 | E65: =E$14 -> 45657 | F65: =F$14 -> 46022 | G65: =G$14 -> 46387 | H65: =H$14 -> 46752 | I65: =I$14 -> 47118 | J65: =J$14 -> 47483 | K65: =K$14 -> 47848
C66: ASSETS
C68: Current Assets
C69: Financial Assets at Amortized Cost (T-Bills) | D69: 5100922 | E69: 15652146 | F69: 201661238 | G69: =F69 -> 201661238 | H69: =G69 -> 201661238 | I69: =H69 -> 201661238 | J69: =I69 -> 201661238 | K69: =J69 -> 201661238
C70: Inventories (Net) | D70: 138912639 | E70: 208473803 | F70: 258826409 | G70: =G198 -> 3.3182922e+08 | H70: =H198 -> 3.9167428e+08 | I70: =I198 -> 4.5052147e+08 | J70: =J198 -> 5.0465951e+08 | K70: =K198 -> 5.5518714e+08
C71: Trade and Notes Receivable (Net) | D71: 16938225 | E71: 27584770 | F71: 31142087 | G71: =G199 -> 38009590 | H71: =H199 -> 44864581 | I71: =I199 -> 51605270 | J71: =J199 -> 57806546 | K71: =K199 -> 63594266
C72: Debtors and Other Debit Balances (Net) | D72: 39168713 | E72: 51382391 | F72: 69499941 | G72: =G200 -> 84826181 | H72: =H200 -> 1.0012449e+08 | I72: =I200 -> 1.1516772e+08 | J72: =J200 -> 1.2900714e+08 | K72: =K200 -> 1.4192362e+08
C73: Due from Related Parties | D73: 4251648 | E73: 3388601 | F73: 0 | G73: =G201 -> 0 | H73: =H201 -> 0 | I73: =I201 -> 0 | J73: =J201 -> 0 | K73: =K201 -> 0
C74: Cash and Cash Equivalents | D74: 66602816 | E74: 77553111 | F74: 104342521 | G74: =G154 -> 1.6267825e+08 | H74: =H154 -> 2.9694625e+08 | I74: =I154 -> 4.4913421e+08 | J74: =J154 -> 6.1192113e+08 | K74: =K154 -> 7.9482994e+08
C75: Total Current Assets | D75: =SUM(D69:D74) -> 270974963 | E75: =SUM(E69:E74) -> 384034822 | F75: =SUM(F69:F74) -> 665472196 | G75: =SUM(G69:G74) -> 8.1900448e+08 | H75: =SUM(H69:H74) -> 1.0352708e+09 | I75: =SUM(I69:I74) -> 1.2680899e+09 | J75: =SUM(J69:J74) -> 1.5050556e+09 | K75: =SUM(K69:K74) -> 1.7571962e+09
C77: Non-Current Assets
C78: Property, Plant and Equipment (Net) | D78: 174116983 | E78: 190534890 | F78: 163149183 | G78: =G165 -> 1.6285983e+08 | H78: =H165 -> 2.1042427e+08 | I78: =I165 -> 2.6012213e+08 | J78: =J165 -> 3.1049345e+08 | K78: =K165 -> 3.6062779e+08
C79: Intangible Assets (Net) | D79: 27899321 | E79: 21004672 | F79: 14066392 | G79: =G302 -> 9066392 | H79: =H302 -> 6066392 | I79: =I302 -> 4066392 | J79: =J302 -> 3066392 | K79: =K302 -> 3066392
C80: Right-of-Use Assets (Net) | D80: 142503563 | E80: 130756082 | F80: 136387942 | G80: =G289 -> 1.3837102e+08 | H80: =H289 -> 1.4071174e+08 | I80: =I289 -> 1.4340415e+08 | J80: =J289 -> 1.4642009e+08 | K80: =K289 -> 1.49738e+08
C81: Deferred Tax Assets | D81: 255064 | E81: 5162949 | F81: 10198171 | G81: =F81 -> 10198171 | H81: =G81 -> 10198171 | I81: =H81 -> 10198171 | J81: =I81 -> 10198171 | K81: =J81 -> 10198171
C82: Projects Under Construction (CWIP) | D82: 11802869 | E82: 10104432 | F82: 34362040 | G82: =F82 -> 34362040 | H82: =G82 -> 34362040 | I82: =H82 -> 34362040 | J82: =I82 -> 34362040 | K82: =J82 -> 34362040
C83: Goodwill | D83: 38905695 | E83: 38905695 | F83: 38905695 | G83: =F83 -> 38905695 | H83: =G83 -> 38905695 | I83: =H83 -> 38905695 | J83: =I83 -> 38905695 | K83: =J83 -> 38905695
C84: Total Non-Current Assets | D84: =SUM(D78:D83) -> 395483495 | E84: =SUM(E78:E83) -> 396468720 | F84: =SUM(F78:F83) -> 397069423 | G84: =SUM(G78:G83) -> 3.9376314e+08 | H84: =SUM(H78:H83) -> 4.4066831e+08 | I84: =SUM(I78:I83) -> 4.9105857e+08 | J84: =SUM(J78:J83) -> 5.4344584e+08 | K84: =SUM(K78:K83) -> 5.9689808e+08
C86: Total Assets | D86: =D75+D84 -> 666458458 | E86: =E75+E84 -> 780503542 | F86: =F75+F84 -> 1062541619 | G86: =G75+G84 -> 1.2127676e+09 | H86: =H75+H84 -> 1.4759392e+09 | I86: =I75+I84 -> 1.7591485e+09 | J86: =J75+J84 -> 2.0485014e+09 | K86: =K75+K84 -> 2.3540943e+09
C88: LIABILITIES AND EQUITY
C90: Current Liabilities
C91: Provisions | D91: 19153725 | E91: 18490310 | F91: 40944049 | G91: =F91 -> 40944049 | H91: =G91 -> 40944049 | I91: =H91 -> 40944049 | J91: =I91 -> 40944049 | K91: =J91 -> 40944049
C92: Current Income Tax Liability | D92: 0 | E92: 22336568 | F92: 69211808 | G92: =-G29*G41 -> 20994294 | H92: =-H29*H41 -> 25302226 | I92: =-I29*I41 -> 29081389 | J92: =-J29*J41 -> 32399761 | K92: =-K29*K41 -> 35909926
C93: Long-Term Loans (Current Portion) | D93: 27922381 | E93: 26285124 | F93: 15935445 | G93: =G229-G231 -> 6441727 | H93: =H229-H231 -> 0 | I93: =I229-I231 -> 0 | J93: =J229-J231 -> 0 | K93: =K229-K231 -> 0
C94: Lease Liabilities (Current Portion) | D94: 28819854 | E94: 31974757 | F94: 31685600 | G94: =G273*G274 -> 33810458 | H94: =H273*H274 -> 36318532 | I94: =I273*I274 -> 39203433 | J94: =J273*J274 -> 42435004 | K94: =K273*K274 -> 45990128
C95: Short-Term Borrowings & Credit Facilities | D95: 51401653 | E95: 1337751 | F95: 0 | G95: 0 | H95: 0 | I95: 0 | J95: 0 | K95: 0
C96: Trade and Notes Payable | D96: 157741673 | E96: 215771496 | F96: 242113642 | G96: =G205 -> 3.4401637e+08 | H96: =H205 -> 4.0605936e+08 | I96: =I205 -> 4.6706784e+08 | J96: =J205 -> 5.2319422e+08 | K96: =K205 -> 5.7557759e+08
C97: Due to Related Parties | D97: 30978907 | E97: 1030309 | F97: 3590464 | G97: =G207 -> 4382238.9 | H97: =H207 -> 5172571.2 | I97: =I207 -> 5949725.4 | J97: =J207 -> 6664688.9 | K97: =K207 -> 7331972.4
C98: Creditors and Other Credit Balances | D98: 88281718 | E98: 104670165 | F98: 134517644 | G98: =G206 -> 1.6418169e+08 | H98: =H206 -> 1.9379169e+08 | I98: =I206 -> 2.2290797e+08 | J98: =J206 -> 2.4969426e+08 | K98: =K206 -> 2.7469421e+08
C99: Dividends payable | D99: 0 | E99: 0 | F99: 80000000 | G99: 0 | H99: =G99 -> 0 | I99: =H99 -> 0 | J99: =I99 -> 0 | K99: =J99 -> 0
C100: Total Current Liabilities | D100: =SUM(D91:D99) -> 404299911 | E100: =SUM(E91:E99) -> 421896480 | F100: =SUM(F91:F99) -> 617998652 | G100: =SUM(G91:G99) -> 6.1477082e+08 | H100: =SUM(H91:H99) -> 7.0758843e+08 | I100: =SUM(I91:I99) -> 8.0515441e+08 | J100: =SUM(J91:J99) -> 8.9533198e+08 | K100: =SUM(K91:K99) -> 9.8044787e+08
C102: Non-Current Liabilities
C103: Long-Term Loans (Non-Current Portion) | D103: 48662296 | E103: 22377172 | F103: 6441727 | G103: =G230 -> 0 | H103: =H230 -> 0 | I103: =I230 -> 0 | J103: =J230 -> 0 | K103: =K230 -> 0
C104: Lease Liabilities (Non-Current Portion) | D104: 148674513 | E104: 140921789 | F104: 151279852 | G104: =G273*(1-G274) -> 1.6142478e+08 | H104: =H273*(1-H274) -> 1.7339934e+08 | I104: =I273*(1-I274) -> 1.8717302e+08 | J104: =J273*(1-J274) -> 2.0260185e+08 | K104: =K273*(1-K274) -> 2.1957544e+08
C105: Fixed Assets Purchase Creditors (Non-Current) | D105: 15092078 | E105: 12222226 | F105: 10000008 | G105: =F105-G106 -> 7777788 | H105: =G105-H106 -> 5555568 | I105: =H105-I106 -> 3333348 | J105: =I105-J106 -> 1111128 | K105: 0
C106: Fixed asset purchase creditors - current | D106: 0 | E106: 0 | F106: 2222220 | G106: =F106 -> 2222220 | H106: =G106 -> 2222220 | I106: =H106 -> 2222220 | J106: =I106 -> 2222220 | K106: =J106 -> 2222220
C107: Total Non-Current Liabilities | D107: =SUM(D103:D106) -> 212428887 | E107: =SUM(E103:E106) -> 175521187 | F107: =SUM(F103:F106) -> 169943807 | G107: =SUM(G103:G106) -> 1.7142479e+08 | H107: =SUM(H103:H106) -> 1.8117713e+08 | I107: =SUM(I103:I106) -> 1.9272859e+08 | J107: =SUM(J103:J106) -> 2.059352e+08 | K107: =SUM(K103:K106) -> 2.2179766e+08
C109: Total Liabilities | D109: =D100+D107 -> 616728798 | E109: =E100+E107 -> 597417667 | F109: =F100+F107 -> 787942459 | G109: =G100+G107 -> 7.8619562e+08 | H109: =H100+H107 -> 8.8876556e+08 | I109: =I100+I107 -> 9.97883e+08 | J109: =J100+J107 -> 1.1012672e+09 | K109: =K100+K107 -> 1.2022455e+09
C111: Equity
C112: Paid-in Share Capital | D112: 92833330 | E112: 92833330 | F112: 100000000 | G112: =F112 -> 100000000 | H112: =G112 -> 100000000 | I112: =H112 -> 100000000 | J112: =I112 -> 100000000 | K112: =J112 -> 100000000
C113: Legal Reserve | D113: 9405590 | E113: 9405590 | F113: 23897012 | G113: =F113 -> 23897012 | H113: =G113 -> 23897012 | I113: =H113 -> 23897012 | J113: =I113 -> 23897012 | K113: =J113 -> 23897012
C114: Retained Earnings / (Accumulated Losses) | D114: -83822569 | E114: -53757977 | F114: 151119171 | G114: =G253 -> 3.0307865e+08 | H114: =H253 -> 4.6366411e+08 | I114: =I253 -> 6.3773749e+08 | J114: =J253 -> 8.236856e+08 | K114: =K253 -> 1.0282773e+09
C115: Net Profit / (Loss) for the Year | D115: 31750161 | E115: 135031718 | F115: 0 | G115: =F115 -> 0 | H115: =G115 -> 0 | I115: =H115 -> 0 | J115: =I115 -> 0 | K115: =J115 -> 0
C116: Equity Attributable to Equity Holders of Parent | D116: =SUM(D112:D115) -> 50166512 | E116: =SUM(E112:E115) -> 183512661 | F116: =SUM(F112:F115) -> 275016183 | G116: =SUM(G112:G115) -> 4.2697566e+08 | H116: =SUM(H112:H115) -> 5.8756113e+08 | I116: =SUM(I112:I115) -> 7.6163451e+08 | J116: =SUM(J112:J115) -> 9.4758261e+08 | K116: =SUM(K112:K115) -> 1.1521743e+09
C117: Non-Controlling Interest (NCI) | D117: -436852 | E117: -426786 | F117: -417023 | G117: =G259 -> -403652.62 | H117: =H259 -> -387538.69 | I117: =I259 -> -369017.98 | J117: =J259 -> -348383.93 | K117: =K259 -> -325514.41
C118: Total Equity | D118: =SUM(D116:D117) -> 49729660 | E118: =SUM(E116:E117) -> 183085875 | F118: =SUM(F116:F117) -> 274599160 | G118: =SUM(G116:G117) -> 4.2657201e+08 | H118: =SUM(H116:H117) -> 5.8717359e+08 | I118: =SUM(I116:I117) -> 7.6126549e+08 | J118: =SUM(J116:J117) -> 9.4723423e+08 | K118: =SUM(K116:K117) -> 1.1518488e+09
...

Sheet DCF
B2: Discounted Cash Flow Valuation
B3: =FSM!C3 -> All amounts are shown in EGP, except per-share data, ratios, and shares outstanding
B4: Most recent fiscal year end | D4: 46022 | F4: Discount rate (WACC) | H4: =WACC!H78 -> 0.24356206 | I4: Link from WACC
B5: End of first fiscal year | D5: =EOMONTH(D4,12) -> 46387 | F5: Share price (Public Co) | H5: 17.03
B6: Most recent quarter end date | D6: 46022 | F6: Share price date | H6: 46274
B7: Valuation date | D7: 46022 | F7: Implied Share Price | H7: =C72 -> 5.0487907
B8: Portion of First Year Cash Flows | D8: =YEARFRAC(D7,D5) -> 1 | F8: Upside / (Downside) | H8: =H7/H5-1 -> -0.70353548 | I8: {=_xlfn.IFS(H8>15%,"BUY",H8>=0,"HOLD",H8<0,"SELL")} -> SELL
F9: Midyear adjustment? | H9: 0
B10: Unlevered Free Cash Flows
C11: LTM | D11: Actual | E11: Forecasts
B12: Fiscal year ended | C12: =D7 -> 46022 | D12: =D4 -> 46022 | E12: =EOMONTH(D12,12) -> 46387 | F12: =EOMONTH(E12,12) -> 46752 | G12: =EOMONTH(F12,12) -> 47118 | H12: =EOMONTH(G12,12) -> 47483 | I12: =EOMONTH(H12,12) -> 47848
B14: Revenue | C14: =E14*(1-$D$8)+D14*$D$8 -> 2877655973 | D14: =FSM!F16 -> 2877655973 | E14: =FSM!G16 -> 3.5122413e+09 | F14: =FSM!H16 -> 4.1456704e+09 | G14: =FSM!I16 -> 4.7685376e+09 | H14: =FSM!J16 -> 5.3415609e+09 | I14: =FSM!K16 -> 5.8763698e+09
B15: % growth | E15: =E14/D14-1 -> 0.22052162 | F15: =F14/E14-1 -> 0.18034897 | G15: =G14/F14-1 -> 0.15024523 | H15: =H14/G14-1 -> 0.1201675 | I15: =I14/H14-1 -> 0.10012223
B16: EBITDA | C16: =E16*(1-$D$8)+D16*$D$8 -> 333679968 | D16: =FSM!F35 -> 333679968 | E16: =FSM!G35 -> 4.5737901e+08 | F16: =FSM!H35 -> 5.4061349e+08 | G16: =FSM!I35 -> 6.224601e+08 | H16: =FSM!J35 -> 6.9775707e+08 | I16: =FSM!K35 -> 7.6803256e+08
B17: % margin | D17: =D16/D14 -> 0.11595548 | E17: =E16/E14 -> 0.13022426 | F17: =F16/F14 -> 0.13040436 | G17: =G16/G14 -> 0.1305348 | H17: =H16/H14 -> 0.13062794 | I17: =I16/I14 -> 0.13069847
B18: EBIT | C18: =E18*(1-$D$8)+D18*$D$8 -> 277129999 | D18: =FSM!F25 -> 277129999 | E18: =FSM!G25 -> 3.7061971e+08 | F18: =FSM!H25 -> 4.4791896e+08 | G18: =FSM!I25 -> 5.1257697e+08 | H18: =FSM!J25 -> 5.7085163e+08 | I18: =FSM!K25 -> 6.2444116e+08
B19: % margin | D19: =D18/D14 -> 0.096304076 | E19: =E18/E14 -> 0.10552228 | F19: =F18/F14 -> 0.108045 | G19: =G18/G14 -> 0.10749144 | H19: =H18/H14 -> 0.10686982 | I19: =I18/I14 -> 0.10626308
B21: Tax on EBIT | D21: =D18*D22 -> 64582257 | E21: =E18*E22 -> 83389435 | F21: =F18*F22 -> 1.0078177e+08 | G21: =G18*G22 -> 1.1532982e+08 | H21: =H18*H22 -> 1.2844162e+08 | I21: =I18*I22 -> 1.4049926e+08
B22: Tax rate | D22: =FSM!F40 -> 0.23303957 | E22: =FSM!G40 -> 0.225 | F22: =FSM!H40 -> 0.225 | G22: =FSM!I40 -> 0.225 | H22: =FSM!J40 -> 0.225 | I22: =FSM!K40 -> 0.225
B23: NOPAT (aka EBIAT) | D23: =D18*(1-D22) -> 2.1254774e+08 | E23: =E18*(1-E22) -> 2.8723028e+08 | F23: =F18*(1-F22) -> 3.471372e+08 | G23: =G18*(1-G22) -> 3.9724715e+08 | H23: =H18*(1-H22) -> 4.4241002e+08 | I23: =I18*(1-I22) -> 4.839419e+08
B25: Depreciation & amortization | E25: =FSM!G174 -> 86759301 | F25: =FSM!H174 -> 92694527 | G25: =FSM!I174 -> 1.0988313e+08 | H25: =FSM!J174 -> 1.2690544e+08 | I25: =FSM!K174 -> 1.4359141e+08
B26: Changes in net working capital | E26: =D32-E32 -> 37161990 | F26: =E32-F32 -> 10444965 | G26: =F32-G32 -> 10270804 | H26: =G32-H32 -> 9448899 | I26: =H32-I32 -> 8818762.7
B27: Capital expenditures | E27: =-FSM!G163 -> -35122413 | F27: =-FSM!H163 -> -82913409 | G27: =-FSM!I163 -> -95370753 | H27: =-FSM!J163 -> -1.0683122e+08 | I27: =-FSM!K163 -> -1.175274e+08
B28: Lease Additons | E28: =-FSM!G269 -> -53366788 | F28: =-FSM!H269 -> -62991433 | G28: =-FSM!I269 -> -72455595 | H28: =-FSM!J269 -> -81162403 | I28: =-FSM!K269 -> -89288563
B30: Unlevered free cash flows (UFCF) | E30: =SUM(E23:E28) -> 3.2266237e+08 | F30: =SUM(F23:F28) -> 3.0437185e+08 | G30: =SUM(G23:G28) -> 3.4957474e+08 | H30: =SUM(H23:H28) -> 3.9077073e+08 | I30: =SUM(I23:I28) -> 4.2953611e+08
B32: Net working capital (WC Assets - WC liabilities) | D32: =FSM!F210 -> -20753313 | E32: =FSM!G210 -> -57915303 | F32: =FSM!H210 -> -68360268 | G32: =FSM!I210 -> -78631072 | H32: =FSM!J210 -> -88079971 | I32: =FSM!K210 -> -96898734
B33: as % of revenue | D33: =D32/D14 -> -0.0072118812 | E33: =E32/E14 -> -0.016489557 | F33: =F32/F14 -> -0.016489557 | G33: =G32/G14 -> -0.016489557 | H33: =H32/H14 -> -0.016489557 | I33: =I32/I14 -> -0.016489557
B35: ="Present value of UFCF on "&TEXT(D7,"mmm dd, yyyy")&" valuation date" -> Present value of UFCF on Dec 31, 2025 valuation date
D36: Val date | E36: Yr 1 - Stub | F36: Year 2 | G36: Year 3 | H36: Year 4 | I36: Year 5
B37: Date for discounting cash flows | D37: =D7 -> 46022 | E37: =IF($H$9=1,AVERAGE(E12,D37),E12) -> 46387 | F37: =IF($H$9=1,AVERAGE(F12,E12),F12) -> 46752 | G37: =IF($H$9=1,AVERAGE(G12,F12),G12) -> 47118 | H37: =IF($H$9=1,AVERAGE(H12,G12),H12) -> 47483 | I37: =IF($H$9=1,AVERAGE(I12,H12),I12) -> 47848
B38: Unlevered free cash flows (UFCF) stub adjusted | C38: =D8 -> 1 | E38: =E30*C38 -> 3.2266237e+08 | F38: =F30 -> 3.0437185e+08 | G38: =G30 -> 3.4957474e+08 | H38: =H30 -> 3.9077073e+08 | I38: =I30 -> 4.2953611e+08
B39: Present value of of unlevered free cash flows | E39: =E38/(1+WACC!D$78)^((E37-$D$37)/365) -> 2.5946623e+08 | F39: =F38/(1+WACC!E$78)^((F37-$D$37)/365) -> 1.9682015e+08 | G39: =G38/(1+WACC!F$78)^((G37-$D$37)/365) -> 1.8166794e+08 | H39: =H38/(1+WACC!G$78)^((H37-$D$37)/365) -> 1.6330249e+08 | I39: =I38/(1+WACC!H$78)^((I37-$D$37)/365) -> 1.4434541e+08
B40: Terminal value - growth in perpetuity approach | E40: Terminal value - EBITDA multiple approach
B41: Long term growth rate | C41: 0.1 | E41: Terminal year EBITDA | I41: =I16 -> 7.6803256e+08
B42: =YEAR(I12)&" FCF x (1+g)" -> 2030 FCF x (1+g) | C42: =I38*(1+C41) -> 4.7248972e+08 | E42: EBITDA multiple | I42: 9.2
B43: ="Terminal value in "&YEAR(I12) -> Terminal value in 2030 | C43: =C42/(WACC!H78-C41) -> 3.2911878e+09 | E43: ="Terminal value in "&YEAR(I12) -> Terminal value in 2030 | I43: =I41*I42 -> 7.0658996e+09
B44: Present value of terminal value | C44: =C43/(1+WACC!H78)^((I37-$D$37)/365) -> 1.1060022e+09 | E44: Present value of terminal value | I44: =I43/(1+WACC!H78)^((I37-D37)/365) -> 2.3744923e+09
B45: Present value of stage 1 cash flows | C45: =SUM(E39:I39) -> 9.4560222e+08 | E45: Present value of stage 1 cash flows | I45: =C45 -> 9.4560222e+08
B46: Total enterprise value (TEV) | C46: =SUM(C44:C45) -> 2.0516044e+09 | E46: Enterprise value (stage 1 + 2) | I46: =SUM(I44:I45) -> 3.3200946e+09
B48: Terminal value as % of TEV | C48: =C44/C46 -> 0.53909135 | E48: Terminal value as % of TEV | I48: =I44/I46 -> 0.71518817
B49: Stage 1 cash flows as % of TEV | C49: =1-C48 -> 0.46090865 | E49: Cash flows as % of TEV | I49: =1-I48 -> 0.28481183
B50: Implied TV exit EBITDA multiple | C50: =C43/I16 -> 4.2852191 | E50: Implied terminal growth rate | I50: =(H4-I38/I43)/(1+I38/I43) -> 0.17229805
B52: Net debt | E52: Shares outstanding
B53: Source doc | C53: Consolidated FS 2025
B54: Source date | C54: 12/31/2025 | G54: Source doc | H54: Date | I54: Shares
B55: Gross debt and equivalents | E55: Basic shares | G55: Consolidated FS 2025 | H55: 12/31/2025 | I55: 400000000
B56: Debt | C56: =FSM!F91+FSM!F93+FSM!F94+FSM!F95+FSM!F99+FSM!F103+FSM!F104+FSM!F105+FSM!F106 -> 338508901 | E56: Restricted stock / RSUs
B57: Convertible debt | E57: Options / warrants
B58: Preferred stock | E58: Convertible debt
B59: Noncontrolling (minority) interests | C59: =FSM!F117 -> -417023 | E59: Convertible preferred stock
B60: Nonoperating assets | E60: Net diluted shares outstanding | I60: =SUM(I55:I59) -> 400000000
B61: Cash | C61: =FSM!F74 -> 104342521
B62: Equity investments
B63: Debt securities (optional cash asset) | C63: =FSM!F69 -> 201661238
B64: Net debt | C64: =SUM(C56:C59)-SUM(C61:C63) -> 32088119
B66: Valuation
C67: Perpetuity | D67: EBITDA
B68: Enterprise value | C68: =C46 -> 2.0516044e+09 | D68: =I46 -> 3.3200946e+09
B69: Net debt | C69: =C64 -> 32088119 | D69: =C64 -> 32088119
B70: Equity value | C70: =C68-C69 -> 2.0195163e+09 | D70: =D68-D69 -> 3.2880064e+09
B71: Shares outstanding | C71: =$I$60 -> 400000000 | D71: =$I$60 -> 400000000
B72: Equity value per share | C72: =C70/C71 -> 5.0487907 | D72: =D70/D71 -> 8.2200161 | E72: =C72/G72 -> 0.096609083 | F72: #VALUE! | G72: {=_FV(F72,"Price")} -> 52.26
C74: Last twelve months (LTM)
C75: Perpetuity | D75: EBITDA
B76: EV / Revenue | C76: =C68/$C$14 -> 0.7129429 | D76: =D68/$C$14 -> 1.1537496
B77: EV / EBITDA | C77: =C68/$C$16 -> 6.1484194 | D77: =D68/$C$16 -> 9.9499367
B78: EV / EBIT | C78: =C68/$C$18 -> 7.4030397 | D78: =D68/$C$18 -> 11.980278
C79: Year 1
C80: Perpetuity | D80: EBITDA
B81: EV / Revenue | C81: =C68/$E$14 -> 0.58412968 | D81: =D68/$E$14 -> 0.94529227
B82: EV / EBITDA | C82: =C68/$E$16 -> 4.4855674 | D82: =D68/$E$16 -> 7.258957
B83: EV / EBIT | C83: =C68/$E$18 -> 5.5356052 | D83: =D68/$E$18 -> 8.9582245
B85: Outputs
D87: Equity value per share | L87: LTM EBITDA multiple
E88: Long term growth rate (g): | L88: Long term growth rate (g):
D89: =C72 -> 5.0487907 | E89: =F89-0.005 -> 0.09 | F89: =G89-0.005 -> 0.095 | G89: 0.1 | H89: =G89+0.005 -> 0.105 | I89: =H89+0.005 -> 0.11 | L89: =C77 -> 6.1484194 | M89: =N89-0.005 -> 0.09 | N89: =O89-0.005 -> 0.095 | O89: 0.1 | P89: =O89+0.005 -> 0.105 | Q89: =P89+0.005 -> 0.11
D90: =D91+0.01 -> 0.2851674 | E90: 4.8452333 | F90: 4.9435865 | G90: 5.0487907 | H90: 5.1615874 | I90: 5.2828294 | L90: =L91+0.01 -> 0.2851674 | M90: 5.9044043 | N90: 6.0223056 | O90: 6.1484194 | P90: 6.2836349 | Q90: 6.4289741
D91: =D92+0.01 -> 0.2751674 | E91: 4.8452333 | F91: 4.9435865 | G91: 5.0487907 | H91: 5.1615874 | I91: 5.2828294 | L91: =L92+0.01 -> 0.2751674 | M91: 5.9044043 | N91: 6.0223056 | O91: 6.1484194 | P91: 6.2836349 | Q91: 6.4289741
C92: WACC: | D92: 0.2651674 | E92: 4.8452333 | F92: 4.9435865 | G92: 5.0487907 | H92: 5.1615874 | I92: 5.2828294 | K92: WACC: | L92: 0.2651674 | M92: 5.9044043 | N92: 6.0223056 | O92: 6.1484194 | P92: 6.2836349 | Q92: 6.4289741
D93: =D92-0.01 -> 0.2551674 | E93: 4.8452333 | F93: 4.9435865 | G93: 5.0487907 | H93: 5.1615874 | I93: 5.2828294 | L93: =L92-0.01 -> 0.2551674 | M93: 5.9044043 | N93: 6.0223056 | O93: 6.1484194 | P93: 6.2836349 | Q93: 6.4289741
B94: Data | D94: =D93-0.01 -> 0.2451674 | E94: 4.8452333 | F94: 4.9435865 | G94: 5.0487907 | H94: 5.1615874 | I94: 5.2828294 | L94: =L93-0.01 -> 0.2451674 | M94: 5.9044043 | N94: 6.0223056 | O94: 6.1484194 | P94: 6.2836349 | Q94: 6.4289741
B95: Tables
D96: Equity value per share | L96: LTM EBITDA multiple
E97: Exit EBITDA Multiple | M97: Exit EBITDA Multiple
D98: =D72 -> 8.2200161 | E98: =+F98-0.5 -> 8.2 | F98: =+G98-0.5 -> 8.7 | G98: 9.2 | H98: =+G98+0.5 -> 9.7 | I98: =+H98+0.5 -> 10.2 | L98: =D77 -> 9.9499367 | M98: =+N98-0.5 -> 8.2 | N98: =+O98-0.5 -> 8.7 | O98: 9.2 | P98: =+O98+0.5 -> 9.7 | Q98: =+P98+0.5 -> 10.2
D99: =D100+0.01 -> 0.2851674 | E99: 7.5747736 | F99: 7.8973949 | G99: 8.2200161 | H99: 8.5426374 | I99: 8.8652586 | L99: =L100+0.01 -> 0.2851674 | M99: 9.1764501 | N99: 9.5631934 | O99: 9.9499367 | P99: 10.33668 | Q99: 10.723423
D100: =D101+0.01 -> 0.2751674 | E100: 7.5747736 | F100: 7.8973949 | G100: 8.2200161 | H100: 8.5426374 | I100: 8.8652586 | L100: =L101+0.01 -> 0.2751674 | M100: 9.1764501 | N100: 9.5631934 | O100: 9.9499367 | P100: 10.33668 | Q100: 10.723423
C101: WACC: | D101: 0.2651674 | E101: 7.5747736 | F101: 7.8973949 | G101: 8.2200161 | H101: 8.5426374 | I101: 8.8652586 | K101: WACC: | L101: 0.2651674 | M101: 9.1764501 | N101: 9.5631934 | O101: 9.9499367 | P101: 10.33668 | Q101: 10.723423
D102: =D101-0.01 -> 0.2551674 | E102: 7.5747736 | F102: 7.8973949 | G102: 8.2200161 | H102: 8.5426374 | I102: 8.8652586 | L102: =L101-0.01 -> 0.2551674 | M102: 9.1764501 | N102: 9.5631934 | O102: 9.9499367 | P102: 10.33668 | Q102: 10.723423
D103: =D102-0.01 -> 0.2451674 | E103: 7.5747736 | F103: 7.8973949 | G103: 8.2200161 | H103: 8.5426374 | I103: 8.8652586 | L103: =L102-0.01 -> 0.2451674 | M103: 9.1764501 | N103: 9.5631934 | O103: 9.9499367 | P103: 10.33668 | Q103: 10.723423
B105: Equity value range | G105: Football field
C126: Low | D126: Diff. | E126: High | O126: Low | P126: Diff. | Q126: High
B127: ="DCF Value at "&TEXT(E98,"0.0x")&"-"&TEXT(I98,"0.0x")&" Exit EBITDA Range at "&TEXT(D101,"0.0%")&" WACC" -> DCF Value at 8.2x-10.2x Exit EBITDA Range at 26.5% WACC | C127: =E101 -> 7.5747736 | D127: =E127-C127 -> 1.290485 | E127: =I101 -> 8.8652586 | G127: ="LTM EBITDA Purchase Multiple at "&TEXT(M89,"0.0%")&"-"&TEXT(Q89,"0.0%")&" Perpetuity Growth at "&TEXT(L92,"0.0%")&" WACC" -> LTM EBITDA Purchase Multiple at 9.0%-11.0% Perpetuity Growth at 26.5% WACC | O127: =M92 -> 5.9044043 | P127: =Q127-O127 -> 0.52456976 | Q127: =Q92 -> 6.4289741
B128: ="DCF Value at "&TEXT(E89,"0.0%")&"-"&TEXT(I89,"0.0%")&" Perpetuity Range at "&TEXT(D101,"0.0%")&" WACC" -> DCF Value at 9.0%-11.0% Perpetuity Range at 26.5% WACC | C128: =E92 -> 4.8452333 | D128: =E128-C128 -> 0.43759605 | E128: =I92 -> 5.2828294 | G128: ="LTM EBITDA Purchase Multiple at "&TEXT(M101,"0.0x")&"-"&TEXT(Q101,"0.0x")&" Exit EBITDA Multiple at "&TEXT(L101,"0.0%")&" WACC" -> LTM EBITDA Purchase Multiple at 9.2x-10.7x Exit EBITDA Multiple at 26.5% WACC | O128: =M101 -> 9.1764501 | P128: =Q128-O128 -> 1.5469733 | Q128: =Q101 -> 10.723423
B129: 52 Week Market High/Low | C129: 0.25 | D129: =E129-C129 -> 18.9 | E129: 19.15 | G129: ="LTM EBITDA Purchase Multiple at "&TEXT(L103,"0.0%")&"-"&TEXT(L99,"0.0%")&" WACC at "&TEXT(O98,"0.0x")&" Exit EBITDA" -> LTM EBITDA Purchase Multiple at 24.5%-28.5% WACC at 9.2x Exit EBITDA | O129: =O99 -> 9.9499367 | P129: =Q129-O129 -> 0 | Q129: =O103 -> 9.9499367

Sheet WACC
B2: WACC Buildup
B3: =DCF!B3 -> All amounts are shown in EGP, except per-share data, ratios, and shares outstanding
B4: Cost of capital assumptions
B6: Cost of debt | C6: 0.2
B7: Tax rate | C7: 0.225
B8: Cost of debt (after tax) | C8: =C6*(1-C7) -> 0.155
B10: Risk free rate | C10: 0.2313
B11: Beta | C11: =IF(C32="Observed",(2/3)*C34+(1/3),C35) -> 0.29172822
B12: Market risk premium | C12: 0.055
B13: Cost of equity | C13: =C10+C11*(C12) -> 0.24734505
B15: Capital weights (capital structure)
D16: Target
C17: Current | D17: (override) | E17: % of total
B18: Equity | C18: =DCF!I60*DCF!H5 -> 6812000000 | E18: =C18/(C18+C19) -> 0.95265947
B19: Debt | C19: =DCF!C56 -> 338508901 | E19: =C19/(C19+C18) -> 0.047340533
B21: Cost of capital (WACC) | E21: =E18*C13+E19*C8 -> 0.24297339
B23: WACC sensitivity to MRP and Beta
D24: Beta
C25: =E21 -> 0.24297339 | D25: =E25-0.1 -> 0.57909163 | E25: 0.67909163 | F25: =E25+0.1 -> 0.77909163
C26: =C27-0.005 -> 0.045 | D26: 0.25251339 | E26: 0.25680036 | F26: 0.26108732
B27: Market | C27: =C28-0.005 -> 0.05 | D27: 0.25527177 | E27: 0.26003507 | F27: 0.26479837
B28: Risk | C28: 0.055 | D28: 0.25803016 | E28: 0.26326979 | F28: 0.26850941
B29: Premium | C29: =C28+0.005 -> 0.06 | D29: 0.26078854 | E29: 0.2665045 | F29: 0.27222046
C30: =C29+0.005 -> 0.065 | D30: 0.26354693 | E30: 0.26973922 | F30: 0.2759315
B32: Select Beta for model | C32: Industry
B34: Observed | C34: 1.18
B35: Industry beta | C35: =C47 -> 0.29172822
B37: Industry beta
C39: Observed b | D39: Share price | E39: Dil. shares | F39: Market cap | G39: Net Debt | H39: Tax rate | I39: Delev. b
B40: Juhayna (JUFO.CA) | C40: 0.23 | D40: 27.33 | E40: 1176756353 | F40: =E40*D40 -> 3.2160751e+10 | G40: 5522542793 | H40: 0.225 | I40: =C40/(1+(1-H40)*(G40/F40)) -> 0.20298645
B41: Edita (EFID.CA) | C41: 0.26 | D41: 21.33 | E41: 1400027312 | F41: =E41*D41 -> 2.9862583e+10 | G41: 627731652 | H41: 0.225 | I41: =C41/(1+(1-H41)*(G41/F41)) -> 0.25583223
B42: Spinneys (SPINNEYS.AE) | C42: 0.46 | D42: 1.3 | E42: 3600000000 | F42: =E42*D42 -> 4680000000 | G42: 233138000 | H42: 0.09 | I42: =C42/(1+(1-H42)*(G42/F42)) -> 0.44005142
B43: BinDawood (4161.SR) | C43: 0.37 | D43: 4.65 | E43: 1143000000 | F43: =E43*D43 -> 5314950000 | G43: 2674660774 | H43: 0.2 | I43: =C43/(1+(1-H43)*(G43/F43)) -> 0.26379829
B44: Gourmet Egypt | C44: 1.18 | D44: 17.03 | E44: 400000000 | F44: =E44*D44 -> 6812000000 | G44: =DCF!C64 -> 32088119 | H44: 0.225
B46: Industry average delevered beta | C46: =AVERAGE(I40:I43) -> 0.2906671
B47: =FSM!Company_Name&" beta" -> Gourmet Egypt beta | C47: =C46*(1+(1-H44)*(G44/F44)) -> 0.29172822
B49: Year-by-Year Cost of Equity and WACC
B50: Fiscal year | C50: =FSM!F$13 -> 2025 | D50: =FSM!G$13 -> 2026 | E50: =FSM!H$13 -> 2027 | F50: =FSM!I$13 -> 2028 | G50: =FSM!J$13 -> 2029 | H50: =FSM!K$13 -> 2030
B51: Fiscal year end date | C51: =FSM!F$14 -> 46022 | D51: =FSM!G$14 -> 46387 | E51: =FSM!H$14 -> 46752 | F51: =FSM!I$14 -> 47118 | G51: =FSM!J$14 -> 47483 | H51: =FSM!K$14 -> 47848
B53: RELEVERED BETA (D/E changes every year)
B55: Unlevered beta (selected on Build-Up tab - held constant) | C55: =$C$47 -> 0.29172822 | D55: =$C$47 -> 0.29172822 | E55: =$C$47 -> 0.29172822 | F55: =$C$47 -> 0.29172822 | G55: =$C$47 -> 0.29172822 | H55: =$C$47 -> 0.29172822
B56: Opening total debt (prior year-end) | C56: =FSM!F93+FSM!F94+FSM!F95+FSM!F103+FSM!F104+FSM!F105 -> 215342632 | D56: =FSM!G93+FSM!G94+FSM!G95+FSM!G103+FSM!G104+FSM!G105 -> 2.0945476e+08 | E56: =FSM!H93+FSM!H94+FSM!H95+FSM!H103+FSM!H104+FSM!H105 -> 2.1527344e+08 | F56: =FSM!I93+FSM!I94+FSM!I95+FSM!I103+FSM!I104+FSM!I105 -> 2.297098e+08 | G56: =FSM!J93+FSM!J94+FSM!J95+FSM!J103+FSM!J104+FSM!J105 -> 2.4614798e+08 | H56: =FSM!K93+FSM!K94+FSM!K95+FSM!K103+FSM!K104+FSM!K105 -> 2.6556557e+08
B57: Opening book equity (prior year-end) | C57: =FSM!F118 -> 274599160 | D57: =FSM!G118 -> 4.2657201e+08 | E57: =FSM!H118 -> 5.8717359e+08 | F57: =FSM!I118 -> 7.6126549e+08 | G57: =FSM!J118 -> 9.4723423e+08 | H57: =FSM!K118 -> 1.1518488e+09
B58: Opening D/E | C58: =$E$19/$E$18 -> 0.049693027 | D58: =$E$19/$E$18 -> 0.049693027 | E58: =$E$19/$E$18 -> 0.049693027 | F58: =$E$19/$E$18 -> 0.049693027 | G58: =$E$19/$E$18 -> 0.049693027 | H58: =$E$19/$E$18 -> 0.049693027
B59: Tax rate | C59: 0.225 | D59: 0.225 | E59: 0.225 | F59: 0.225 | G59: 0.225 | H59: 0.225
B60: Relevered beta = βu × [1 + (1 - t) × D/E] | C60: =C55*(1+(1-C59)*(C58)) -> 0.30296329 | D60: =D55*(1+(1-D59)*(D58)) -> 0.30296329 | E60: =E55*(1+(1-E59)*(E58)) -> 0.30296329 | F60: =F55*(1+(1-F59)*(F58)) -> 0.30296329 | G60: =G55*(1+(1-G59)*(G58)) -> 0.30296329 | H60: =H55*(1+(1-H59)*(H58)) -> 0.30296329
B62: CAPM
B64: Risk-free rate (EGP 10Y, held flat) | C64: =C10 -> 0.2313 | D64: =C64 -> 0.2313 | E64: =D64 -> 0.2313 | F64: =E64 -> 0.2313 | G64: =F64 -> 0.2313 | H64: =G64 -> 0.2313
B65: Mature-market ERP (held flat) | C65: =C12 -> 0.055 | D65: =C65 -> 0.055 | E65: =D65 -> 0.055 | F65: =E65 -> 0.055 | G65: =F65 -> 0.055 | H65: =G65 -> 0.055
B66: Cost of equity Ke | C66: =C64+C60*(C65) -> 0.24796298 | D66: =D64+D60*(D65) -> 0.24796298 | E66: =E64+E60*(E65) -> 0.24796298 | F66: =F64+F60*(F65) -> 0.24796298 | G66: =G64+G60*(G65) -> 0.24796298 | H66: =H64+H60*(H65) -> 0.24796298
B68: COST OF DEBT BY YEAR (each year's realised rate from the debt schedule)
B70: Pre-tax Kd(t) = interest expense(t) / average debt(t) | C70: =C6 -> 0.2 | D70: =C70 -> 0.2 | E70: =D70 -> 0.2 | F70: =E70 -> 0.2 | G70: =F70 -> 0.2 | H70: =G70 -> 0.2
B71: After-tax Kd(t) | C71: =C70*(1-C59) -> 0.155 | D71: =D70*(1-D59) -> 0.155 | E71: =E70*(1-E59) -> 0.155 | F71: =F70*(1-F59) -> 0.155 | G71: =G70*(1-G59) -> 0.155 | H71: =H70*(1-H59) -> 0.155
B73: WEIGHTS AND WACC BY YEAR
B75: Target Market Equity Weight | C75: =$E$18 -> 0.95265947 | D75: =$E$18 -> 0.95265947 | E75: =D75 -> 0.95265947 | F75: =E75 -> 0.95265947 | G75: =F75 -> 0.95265947 | H75: =G75 -> 0.95265947
B76: Target Market Debt Weight | C76: =$E$19 -> 0.047340533 | D76: =$E$19 -> 0.047340533 | E76: =D76 -> 0.047340533 | F76: =E76 -> 0.047340533 | G76: =F76 -> 0.047340533 | H76: =G76 -> 0.047340533
B78: WACC(t) = E-weight × Ke(t) + D-weight × Kd(t) × (1 - tax) | C78: =C75*C66+C76*C71 -> 0.24356206 | D78: =D75*D66+D76*D71 -> 0.24356206 | E78: =E75*E66+E76*E71 -> 0.24356206 | F78: =F75*F66+F76*F71 -> 0.24356206 | G78: =G75*G66+G76*G71 -> 0.24356206 | H78: =H75*H66+H76*H71 -> 0.24356206

Sheet Trading Comps
B2: Comparable Companies Analysis (Trading Comps)
B4: Refresh date: | C4: 46274
B6: GENERAL INFORMATION
B7: Ticker | C7: JUFO.CA | D7: EFID.CA | E7: SPINNEYS.AE | F7: 4161.SR | G7: GOUR.CA
B8: Company | C8: Juhayna Food Industries | D8: Edita Food Industries | E8: Spinneys 1961 Holding | F8: BinDawood Holding | G8: Gourmet Egypt.com for Food S.A.E.
B9: Exchange / Currency | C9: EGX / EGP | D9: EGX / EGP | E9: DFM / AED | F9: Tadawul / SAR | G9: EGX / EGP
B10: Fiscal year end | C10: 46387 | D10: 46387 | E10: 46387 | F10: 46387 | G10: 46387
B11: Last closing price | C11: 27.33 | D11: 21.33 | E11: 1.3 | F11: 4.65 | G11: 17.03
B12: Price as of | C12: 46213 | D12: 46213 | E12: 46213 | F12: 46213 | G12: 46274
B14: FULLY DILUTED SHARES
B15: Basic shares outstanding | C15: 1176756353 | D15: 1400027312 | E15: 3600000000 | F15: 1143000000 | G15: =FSM!D10 -> 400000000
B16: Options / RSUs / other dilution | C16: 0 | D16: 0 | E16: 0 | F16: 0 | G16: 0
B17: Fully diluted shares | C17: =SUM(C15:C16) -> 1176756353 | D17: =SUM(D15:D16) -> 1400027312 | E17: =SUM(E15:E16) -> 3600000000 | F17: =SUM(F15:F16) -> 1143000000 | G17: =SUM(G15:G16) -> 400000000
B19: BALANCE SHEET DATA (latest reported)
B20: Total debt (incl. leases) | C20: 7260901976 | D20: 5001054285 | E20: 1035610000 | F20: 2825448637 | G20: =DCF!C56 -> 338508901
B21: Minority interest | C21: 1114421 | D21: 367793335 | E21: -26013000 | F21: 133933747 | G21: =DCF!C59 -> -417023
B22: Cash + liquid investments | C22: 1739473604 | D22: 4741115968 | E22: 776459000 | F22: 284721610 | G22: =DCF!C61+DCF!C63 -> 306003759
B23: Net debt / (net cash) | C23: =SUM(C20:C21)-C22 -> 5522542793 | D23: =SUM(D20:D21)-D22 -> 627731652 | E23: =SUM(E20:E21)-E22 -> 233138000 | F23: =SUM(F20:F21)-F22 -> 2674660774 | G23: =SUM(G20:G21)-G22 -> 32088119
B25: MARKET VALUATION
B26: Market capitalization | C26: =C11*C17 -> 3.2160751e+10 | D26: =D11*D17 -> 2.9862583e+10 | E26: =E11*E17 -> 4680000000 | F26: =F11*F17 -> 5314950000 | G26: =G11*G17 -> 6812000000
B27: Enterprise value (EV) | C27: =C26+C23 -> 3.7683294e+10 | D27: =D26+D23 -> 3.0490314e+10 | E27: =E26+E23 -> 4913138000 | F27: =F26+F23 -> 7989610774 | G27: =G26+G23 -> 6844088119
B29: LTM FINANCIALS
B30: Revenue | C30: 29984446222 | D30: 20915072432 | E30: 3646759000 | F30: 6347958607 | G30: =FSM!F16 -> 2877655973
B31: EBITDA | C31: 4095464106 | D31: 4218459783 | E31: 731009000 | F31: 911892371 | G31: =FSM!F20 -> 361759057
B32: EBIT | C32: 3573292094 | D32: 3740483615 | E32: 426514000 | F32: 395727489 | G32: =FSM!F25 -> 277129999
B33: Net income | C33: 1909608115 | D33: 2749571345 | E33: 341405000 | F33: 269931705 | G33: =FSM!F31 -> 211212632
B34: EBITDA margin | C34: =C31/C30 -> 0.13658628 | D34: =D31/D30 -> 0.20169473 | E34: =E31/E30 -> 0.20045443 | F34: =F31/F30 -> 0.14365128 | G34: =G31/G30 -> 0.1257131
B36: TRADING MULTIPLES
B37: EV / Revenue (LTM) | C37: =C27/C30 -> 1.2567614 | D37: =D27/D30 -> 1.4578154 | E37: =E27/E30 -> 1.3472615 | F37: =F27/F30 -> 1.258611 | G37: =G27/G30 -> 2.3783552
B38: EV / EBITDA (LTM) | C38: =C27/C31 -> 9.2012268 | D38: =D27/D31 -> 7.227831 | E38: =E27/E31 -> 6.7210363 | F38: =F27/F31 -> 8.7615721 | G38: =G27/G31 -> 18.918913
B39: EV / EBIT (LTM) | C39: =C27/C32 -> 10.54582 | D39: =D27/D32 -> 8.1514364 | E39: =E27/E32 -> 11.519289 | F39: =F27/F32 -> 20.189678 | G39: =G27/G32 -> 24.696309
B40: P / E (LTM) | C40: =C26/C33 -> 16.841545 | D40: =D26/D33 -> 10.860814 | E40: =E26/E33 -> 13.708059 | F40: =F26/F33 -> 19.68998 | G40: =G26/G33 -> 32.251859
B42: PEER STATISTICS
C43: EV/Revenue | D43: EV/EBITDA | E43: EV/EBIT | F43: P/E
B44: Mean | C44: =AVERAGE(C37:F37) -> 1.3301123 | D44: =AVERAGE(C38:F38) -> 7.9779165 | E44: =AVERAGE(C39:F39) -> 12.601556 | F44: =AVERAGE(C40:F40) -> 15.2751
B45: Median | C45: =MEDIAN(C37:F37) -> 1.3029363 | D45: =MEDIAN(C38:F38) -> 7.9947015 | E45: =MEDIAN(C39:F39) -> 11.032554 | F45: =MEDIAN(C40:F40) -> 15.274802
B46: High | C46: =MAX(C37:F37) -> 1.4578154 | D46: =MAX(C38:F38) -> 9.2012268 | E46: =MAX(C39:F39) -> 20.189678 | F46: =MAX(C40:F40) -> 19.68998
B47: Low | C47: =MIN(C37:F37) -> 1.2567614 | D47: =MIN(C38:F38) -> 6.7210363 | E47: =MIN(C39:F39) -> 8.1514364 | F47: =MIN(C40:F40) -> 10.860814
B49: IMPLIED VALUATION (from peer MEDIAN multiples)
B50: Via EV/EBITDA:
B51: Peer median EV/EBITDA | C51: =D45 -> 7.9947015
B52: x LTM EBITDA | C52: =G31 -> 361759057
B53: Implied Enterprise Value | C53: =C51*C52 -> 2.8921557e+09
B54: Less: net debt / plus net cash | C54: =G23 -> 32088119
B55: Implied equity value | C55: =C53-C54 -> 2.8600676e+09
B56: Fully diluted shares | C56: =G17 -> 400000000
B57: Implied value per share (EGP) | C57: =C55/C56 -> 7.1501689
B59: Via P/E:
B60: Peer median P/E | C60: =F45 -> 15.274802
B61: x LTM net income | C61: =G33 -> 211212632
B62: Implied equity value | C62: =C60*C61 -> 3.2262312e+09
B63: Fully diluted shares | C63: =C56 -> 400000000
B64: Implied value per share (EGP) | C64: =C62/C63 -> 8.0655779
B66: Via (closest Egyptian peer):
B67: EV/EBITDA | C67: =D38 -> 7.227831
B68: x LTM EBITDA | C68: =C52 -> 361759057
B69: Implied Enterprise Value | C69: =C67*C68 -> 2.6147333e+09
B70: Less: net debt / plus net cash | C70: =C54 -> 32088119
B71: Implied equity value | C71: =C69-C70 -> 2.5826452e+09
B72: Fully diluted shares | C72: =C63 -> 400000000
B73: Implied value per share (EGP) | C73: =C71/C72 -> 6.456613
