Workbook
Name Company_Name: FSM!$D$5
Name Company_Name: #REF!
Name Hist_Yr: FSM!#REF!
Name Hist_Yr: #REF!
Name IQ_CH: 110000
Name IQ_CQ: 5000
Name IQ_CY: 10000
Name IQ_DAILY: 500000
Name IQ_FH: 100000
Name IQ_FQ: 500
Name IQ_FY: 1000
Name IQ_LTM: 2000
Name IQ_MONTH: 15000
Name IQ_NTM: 6000
Name IQ_WEEK: 50000
Name IQ_YTD: 3000

Sheet FSM
C2: =Company_Name&" - Financial Statement Model" -> Oriental Weavers - Financial Statement Model
C3: All amounts are shown in EGP, except per-share data, ratios, and shares outstanding
C5: Company Name | D5: Oriental Weavers
C6: Ticker | D6: ORWE.CA
C7: Latest Closing Share Price | D7: 23.48
C8: Latest Closing Share Price Date | D8: 46190
C9: Last Historical Year | D9: 46022
C10: Shares outstanding | D10: 665107268
C12: INCOME STATEMENT
C13: Fiscal year | D13: =E13-1 -> 2023 | E13: =F13-1 -> 2024 | F13: =YEAR(D9) -> 2025 | G13: =F13+1 -> 2026 | H13: =G13+1 -> 2027 | I13: =H13+1 -> 2028 | J13: =I13+1 -> 2029 | K13: =J13+1 -> 2030
C14: Fiscal year end date | D14: =EOMONTH(E14,-12) -> 45291 | E14: =EOMONTH(F14,-12) -> 45657 | F14: =D9 -> 46022 | G14: =EOMONTH(F14,12) -> 46387 | H14: =EOMONTH(G14,12) -> 46752 | I14: =EOMONTH(H14,12) -> 47118 | J14: =EOMONTH(I14,12) -> 47483 | K14: =EOMONTH(J14,12) -> 47848
C16: Net Sales (Revenues) | D16: 17658543016 | E16: 24288877875 | F16: 26622797999 | G16: =G183 -> 28494670000 | H16: =H183 -> 3.0451784e+10 | I16: =I183 -> 3.2500681e+10 | J16: =J183 -> 3.4424825e+10 | K16: =K183 -> 3.6420561e+10
C17: Cost of Sales (COGS) | D17: -15108838958 | E17: -21185701953 | F17: -23272535382 | G17: =G18-G16 -> -2.4908848e+10 | H17: =H18-H16 -> -2.6619675e+10 | I17: =I18-I16 -> -2.8410735e+10 | J17: =J18-J16 -> -3.0092741e+10 | K17: =K18-K16 -> -3.1837329e+10
C18: Gross Profit | D18: =SUM(D16:D17) -> 2549704058 | E18: =SUM(E16:E17) -> 3103175922 | F18: =SUM(F16:F17) -> 3350262617 | G18: =G16*G47 -> 3.5858225e+09 | H18: =H16*H47 -> 3.8321094e+09 | I18: =I16*I47 -> 4.0899464e+09 | J18: =J16*J47 -> 4.3320843e+09 | K18: =K16*K47 -> 4.5832314e+09
C19: Selling & Distribution Expenses | D19: -208574673 | E19: -254754592 | F19: -299019544 | G19: =G$16*G48 -> -3.1849237e+08 | H19: =H$16*H48 -> -3.4036754e+08 | I19: =I$16*I48 -> -3.632686e+08 | J19: =J$16*J48 -> -3.8477526e+08 | K19: =K$16*K48 -> -4.0708212e+08
C20: General & Administrative Expenses | D20: -513145476 | E20: -630066477 | F20: -752483532 | G20: =G$16*G49 -> -7.9086479e+08 | H20: =H$16*H49 -> -8.4518416e+08 | I20: =I$16*I49 -> -9.0205097e+08 | J20: =J$16*J49 -> -9.5545526e+08 | K20: =K$16*K49 -> -1.0108466e+09
C21: Expected Credit Loss (ECL) | D21: -68304458 | E21: -24331700 | F21: -253260437 | G21: =G$16*G50 -> -1.3661055e+08 | H21: =H$16*H50 -> -1.4599344e+08 | I21: =I$16*I50 -> -1.5581637e+08 | J21: =J$16*J50 -> -1.6504119e+08 | K21: =K$16*K50 -> -1.7460924e+08
C22: Formed Provisions & Impairment | D22: -98471317 | E22: -145206693 | F22: -150112954 | G22: =G$16*G51 -> -1.6330527e+08 | H22: =H$16*H51 -> -1.7452165e+08 | I22: =I$16*I51 -> -1.8626405e+08 | J22: =J$16*J51 -> -1.9729148e+08 | K22: =K$16*K51 -> -2.087292e+08
C23: Provision No Longer Required | D23: 0 | E23: 0 | F23: 25647760 | G23: 0 | H23: 0 | I23: 0 | J23: 0 | K23: 0
C24: Reverse of Impairment (Assets Held for Sale) | D24: 252358760 | E24: 0 | F24: 0 | G24: 0 | H24: 0 | I24: 0 | J24: 0 | K24: 0
C25: Gain on Sale of Assets Held for Sale | D25: 34761620 | E25: 0 | F25: 918596 | G25: 0 | H25: 0 | I25: 0 | J25: 0 | K25: 0
C26: Capital Gain | D26: 24368149 | E26: 42177712 | F26: 14593979 | G26: 0 | H26: 0 | I26: 0 | J26: 0 | K26: 0
C27: Other Operating Revenues | D27: 329050807 | E27: 594252959 | F27: 454183569 | G27: =G$16*G52 -> 5.7141394e+08 | H27: =H$16*H52 -> 6.1066066e+08 | I27: =I$16*I52 -> 6.5174794e+08 | J27: =J$16*J52 -> 6.9033349e+08 | K27: =K$16*K52 -> 7.303547e+08
C28: Operating Profit (EBIT) | D28: =SUM(D18:D27) -> 2301747470 | E28: =SUM(E18:E27) -> 2685247131 | F28: =SUM(F18:F27) -> 2390730054 | G28: =SUM(G18:G27) -> 2.7479634e+09 | H28: =SUM(H18:H27) -> 2.9367032e+09 | I28: =SUM(I18:I27) -> 3.1342944e+09 | J28: =SUM(J18:J27) -> 3.3198546e+09 | K28: =SUM(K18:K27) -> 3.512319e+09
C29: Financial Investments Income | D29: 51753278 | E29: 177096014 | F29: 18508874 | G29: 0 | H29: 0 | I29: 0 | J29: 0 | K29: 0
C30: Treasury Bills Returns | D30: 240967663 | E30: 579166115 | F30: 430930850 | G30: 0 | H30: 0 | I30: 0 | J30: 0 | K30: 0
C31: Financial Assets at Amortized Cost Returns | D31: 15012317 | E31: 50722790 | F31: 131952040 | G31: 0 | H31: 0 | I31: 0 | J31: 0 | K31: 0
C32: Interest Income | D32: 101662197 | E32: 216179494 | F32: 253316404 | G32: =G240 -> 2.5613413e+08 | H32: =H240 -> 2.3955147e+08 | I32: =I240 -> 2.4138424e+08 | J32: =J240 -> 2.4624853e+08 | K32: =K240 -> 2.543303e+08
C33: Finance Expenses (Interest Expense) | D33: -459366283 | E33: -552552323 | F33: -535526807 | G33: =G239 -> -6.2702751e+08 | H33: =H239 -> -6.3100094e+08 | I33: =I239 -> -6.3516072e+08 | J33: =J239 -> -6.3906721e+08 | K33: =K239 -> -6.4311905e+08
C34: Foreign Exchange Differences | D34: -166163055 | E34: -351533473 | F34: -51440512 | G34: 0 | H34: 0 | I34: 0 | J34: 0 | K34: 0
C35: Net Profit Before Income Tax (EBT) | D35: =SUM(D28:D34) -> 2085613587 | E35: =SUM(E28:E34) -> 2804325748 | F35: =SUM(F28:F34) -> 2638470903 | G35: =SUM(G28:G34) -> 2.3770701e+09 | H35: =SUM(H28:H34) -> 2.5452538e+09 | I35: =SUM(I28:I34) -> 2.7405179e+09 | J35: =SUM(J28:J34) -> 2.9270359e+09 | K35: =SUM(K28:K34) -> 3.1235302e+09
C36: Current Income Tax | D36: -234454961 | E36: -426367543 | F36: -343889121 | G36: =G35*G53 -> -2.6041036e+08 | H36: =H35*H53 -> -2.7883505e+08 | I36: =I35*I53 -> -3.0022643e+08 | J36: =J35*J53 -> -3.2065966e+08 | K36: =K35*K53 -> -3.421858e+08
C37: Deferred Tax | D37: 40823397 | E37: 163723612 | F37: -31181909 | G37: 0 | H37: 0 | I37: 0 | J37: 0 | K37: 0
C38: Net Profit for the Year | D38: =SUM(D35:D37) -> 1891982023 | E38: =SUM(E35:E37) -> 2541681817 | F38: =SUM(F35:F37) -> 2263399873 | G38: =SUM(G35:G37) -> 2.1166597e+09 | H38: =SUM(H35:H37) -> 2.2664187e+09 | I38: =SUM(I35:I37) -> 2.4402915e+09 | J38: =SUM(J35:J37) -> 2.6063763e+09 | K38: =SUM(K35:K37) -> 2.7813444e+09
C39: Parent Company Shareholders | D39: =D38-D40 -> 1740203598 | E39: =E38-E40 -> 2192283305 | F39: =F38-F40 -> 2189343558 | G39: =G38-G40 -> 2.0474046e+09 | H39: =H38-H40 -> 2.1922636e+09 | I39: =I38-I40 -> 2.3604475e+09 | J39: =J38-J40 -> 2.5210981e+09 | K39: =K38-K40 -> 2.6903414e+09
C40: Non-controlling Interest | D40: 151778425 | E40: 349398512 | F40: 74056315 | G40: =G255 -> 69255115 | H40: =H255 -> 74155089 | I40: =I255 -> 79844042 | J40: =J255 -> 85278180 | K40: =K255 -> 91002974
C42: EBITDA | D42: =D28+D164 -> 3202947781 | E42: =E28+E164 -> 3981039203 | F42: =F28+F164 -> 3667611139 | G42: =G28+G164 -> 4.1159835e+09 | H42: =H28+H164 -> 4.3986837e+09 | I42: =I28+I164 -> 4.6946418e+09 | J42: =J28+J164 -> 4.9725796e+09 | K42: =K28+K164 -> 5.2608586e+09
C43: EBITDA margin % | D43: =D42/D16 -> 0.18138234 | E43: =E42/E16 -> 0.16390379 | F43: =F42/F16 -> 0.13776205 | G43: =G42/G16 -> 0.14444749 | H43: =H42/H16 -> 0.14444749 | I43: =I42/I16 -> 0.14444749 | J43: =J42/J16 -> 0.14444749 | K43: =K42/K16 -> 0.14444749
C45: Growth Rates & Margins
C46: Revenue growth | D46: =(D16/13255653997)-1 -> 0.33215178 | E46: =E16/D16-1 -> 0.37547463 | F46: =F16/E16-1 -> 0.096090076 | G46: =G16/F16-1 -> 0.070310867 | H46: =H16/G16-1 -> 0.068683517 | I46: =I16/H16-1 -> 0.067283326 | J46: =J16/I16-1 -> 0.059203183 | K46: =K16/J16-1 -> 0.057973733
C47: Gross Margin % of Revenue | D47: =D18/D16 -> 0.14438927 | E47: =E18/E16 -> 0.12776119 | F47: =F18/F16 -> 0.12584187 | G47: =F47 -> 0.12584187 | H47: =G47 -> 0.12584187 | I47: =H47 -> 0.12584187 | J47: =I47 -> 0.12584187 | K47: =J47 -> 0.12584187
C48: Selling & Distribution Expenses | D48: =D19/D16 -> -0.011811545 | E48: =E19/E16 -> -0.010488529 | F48: =F19/F16 -> -0.01123171 | G48: =AVERAGE(D48:G48) -> -0.011177261 | H48: =G48 -> -0.011177261 | I48: =H48 -> -0.011177261 | J48: =I48 -> -0.011177261 | K48: =J48 -> -0.011177261
C49: General & Administrative Expenses | D49: =D20/D16 -> -0.029059333 | E49: =E20/E16 -> -0.025940535 | F49: =F20/F16 -> -0.02826463 | G49: =AVERAGE(D49:G49) -> -0.027754832 | H49: =G49 -> -0.027754832 | I49: =H49 -> -0.027754832 | J49: =I49 -> -0.027754832 | K49: =J49 -> -0.027754832
C50: Expected Credit Loss (ECL) | D50: =D21/D16 -> -0.0038680687 | E50: =E21/E16 -> -0.001001763 | F50: =F21/F16 -> -0.0095129158 | G50: =AVERAGE(D50:G50) -> -0.0047942492 | H50: =G50 -> -0.0047942492 | I50: =H50 -> -0.0047942492 | J50: =I50 -> -0.0047942492 | K50: =J50 -> -0.0047942492
C51: Formed Provisions & Impairment | D51: =D22/D16 -> -0.0055764123 | E51: =E22/E16 -> -0.0059783204 | F51: =F22/F16 -> -0.0056385115 | G51: =AVERAGE(D51:G51) -> -0.0057310814 | H51: =G51 -> -0.0057310814 | I51: =H51 -> -0.0057310814 | J51: =I51 -> -0.0057310814 | K51: =J51 -> -0.0057310814
C52: Other Operating Revenues | D52: =D27/D16 -> 0.018634086 | E52: =E27/E16 -> 0.024466052 | F52: =F27/F16 -> 0.017059949 | G52: =AVERAGE(D52:G52) -> 0.020053362 | H52: =G52 -> 0.020053362 | I52: =H52 -> 0.020053362 | J52: =I52 -> 0.020053362 | K52: =J52 -> 0.020053362
C53: Tax rate | D53: =SUM(D36:D37)/D35 -> -0.092841534 | E53: =SUM(E36:E37)/E35 -> -0.093656713 | F53: =SUM(F36:F37)/F35 -> -0.1421547 | G53: =AVERAGE(D53:G53) -> -0.10955098 | H53: =G53 -> -0.10955098 | I53: =H53 -> -0.10955098 | J53: =I53 -> -0.10955098 | K53: =J53 -> -0.10955098
C55: BALANCE SHEET
C56: Fiscal year | D56: =D$13 -> 2023 | E56: =E$13 -> 2024 | F56: =F$13 -> 2025 | G56: =G$13 -> 2026 | H56: =H$13 -> 2027 | I56: =I$13 -> 2028 | J56: =J$13 -> 2029 | K56: =K$13 -> 2030
C57: Fiscal year end date | D57: =D$14 -> 45291 | E57: =E$14 -> 45657 | F57: =F$14 -> 46022 | G57: =G$14 -> 46387 | H57: =H$14 -> 46752 | I57: =I$14 -> 47118 | J57: =J$14 -> 47483 | K57: =K$14 -> 47848
C58: ASSETS
C60: Current Assets
C61: Inventory | D61: 6927440585 | E61: 11460683769 | F61: 10152672252 | G61: =G203 -> 1.1920684e+10 | H61: =H203 -> 1.2739439e+10 | I61: =I203 -> 1.3596591e+10 | J61: =J203 -> 1.4401552e+10 | K61: =K203 -> 1.5236464e+10
C62: Trades and notes receivable | D62: 3162570053 | E62: 4993106186 | F62: 4534598797 | G62: =G204 -> 5.2714676e+09 | H62: =H204 -> 5.6335305e+09 | I62: =I204 -> 6.0125732e+09 | J62: =J204 -> 6.3685367e+09 | K62: =K204 -> 6.7377445e+09
C63: Debtors and other debit accounts | D63: 714653249 | E63: 1246108062 | F63: 1371760380 | G63: =G205 -> 1.46821e+09 | H63: =H205 -> 1.5690519e+09 | I63: =I205 -> 1.6746229e+09 | J63: =J205 -> 1.7737659e+09 | K63: =K205 -> 1.8765977e+09
C64: Assets held for sale | D64: 0 | E64: 6753971 | F64: 69259868 | G64: =F64 -> 69259868 | H64: =G64 -> 69259868 | I64: =H64 -> 69259868 | J64: =I64 -> 69259868 | K64: =J64 -> 69259868
C65: Treasury bills | D65: 2127279974 | E65: 1784491840 | F65: 805438717 | G65: =F65 -> 805438717 | H65: =G65 -> 805438717 | I65: =H65 -> 805438717 | J65: =I65 -> 805438717 | K65: =J65 -> 805438717
C66: Financial assets at amortized cost | D66: 628791306 | E66: 397440655 | F66: 492146156 | G66: =F66 -> 492146156 | H66: =G66 -> 492146156 | I66: =H66 -> 492146156 | J66: =I66 -> 492146156 | K66: =J66 -> 492146156
C67: Financial assets at fair value through P&L | D67: 0 | E67: 0 | F67: 903865786 | G67: =F67 -> 903865786 | H67: =G67 -> 903865786 | I67: =H67 -> 903865786 | J67: =I67 -> 903865786 | K67: =J67 -> 903865786
C68: Cash at banks and on hand | D68: 1799725616 | E68: 4093643341 | F68: 4632540191 | G68: =G144 -> 3.7712649e+09 | H68: =H144 -> 3.8034072e+09 | I68: =I144 -> 3.8629033e+09 | J68: =J144 -> 4.046622e+09 | K68: =K144 -> 4.2669919e+09
C69: Total Current Assets | D69: =SUM(D61:D68) -> 15360460783 | E69: =SUM(E61:E68) -> 23982227824 | F69: =SUM(F61:F68) -> 22962282147 | G69: =SUM(G61:G68) -> 2.4702337e+10 | H69: =SUM(H61:H68) -> 2.6016139e+10 | I69: =SUM(I61:I68) -> 2.74174e+10 | J69: =SUM(J61:J68) -> 2.8861187e+10 | K69: =SUM(K61:K68) -> 3.0388508e+10
C71: Non-Current Assets
C72: Fixed assets (Net) | D72: 6374016607 | E72: 8898631092 | F72: 8145992227 | G72: =G155 -> 7.9926467e+09 | H72: =H155 -> 7.8287689e+09 | I72: =I155 -> 7.6538649e+09 | J72: =J155 -> 7.468606e+09 | K72: =K155 -> 7.2726069e+09
C73: Projects in progress | D73: 269337810 | E73: 364395705 | F73: 432892831 | G73: =F73 -> 432892831 | H73: =G73 -> 432892831 | I73: =H73 -> 432892831 | J73: =I73 -> 432892831 | K73: =J73 -> 432892831
C74: Right of use assets | D74: 455071409 | E74: 540749442 | F74: 518695424 | G74: =G270 -> 5.7635512e+08 | H74: =H270 -> 6.3797509e+08 | I74: =I270 -> 7.0374105e+08 | J74: =J270 -> 7.7340057e+08 | K74: =K270 -> 8.4709851e+08
C75: Deferred tax assets | D75: 0 | E75: 57080859 | F75: 8110231 | G75: =F75 -> 8110231 | H75: =G75 -> 8110231 | I75: =H75 -> 8110231 | J75: =I75 -> 8110231 | K75: =J75 -> 8110231
C76: Investments at fair value through OCI | D76: 649105349 | E76: 1061481664 | F76: 1010593966 | G76: =F76 -> 1010593966 | H76: =G76 -> 1010593966 | I76: =H76 -> 1010593966 | J76: =I76 -> 1010593966 | K76: =J76 -> 1010593966
C77: Total Non-Current Assets | D77: =SUM(D72:D76) -> 7747531175 | E77: =SUM(E72:E76) -> 10922338762 | F77: =SUM(F72:F76) -> 10116284679 | G77: =SUM(G72:G76) -> 1.0020599e+10 | H77: =SUM(H72:H76) -> 9.9183411e+09 | I77: =SUM(I72:I76) -> 9.809203e+09 | J77: =SUM(J72:J76) -> 9.6936036e+09 | K77: =SUM(K72:K76) -> 9.5713025e+09
C79: Total Assets | D79: =D69+D77 -> 23107991958 | E79: =E69+E77 -> 34904566586 | F79: =F69+F77 -> 33078566826 | G79: =G69+G77 -> 3.4722936e+10 | H79: =H69+H77 -> 3.593448e+10 | I79: =I69+I77 -> 3.7226603e+10 | J79: =J69+J77 -> 3.8554791e+10 | K79: =K69+K77 -> 3.9959811e+10
C81: LIABILITIES AND EQUITY
C83: Current Liabilities
C84: Provisions | D84: 225516257 | E84: 325910581 | F84: 241136369 | G84: =G209 -> 2.5809088e+08 | H84: =H209 -> 2.7581747e+08 | I84: =I209 -> 2.9437538e+08 | J84: =J209 -> 3.1180334e+08 | K84: =K209 -> 3.2987974e+08
C85: Banks-Credit accounts | D85: 4190742160 | E85: 6949328786 | F85: 6613356814 | G85: =F85 -> 6613356814 | H85: =G85 -> 6613356814 | I85: =H85 -> 6613356814 | J85: =I85 -> 6613356814 | K85: =J85 -> 6613356814
C86: Lease contracts liabilities - current | D86: 114568544 | E86: 159721246 | F86: 182414674 | G86: =G283*G284 -> 2.1607012e+08 | H86: =H283*H284 -> 2.5203714e+08 | I86: =I283*I284 -> 2.9042414e+08 | J86: =J283*J284 -> 3.3108377e+08 | K86: =K283*K284 -> 3.7410059e+08
C87: Long term liabilities - current portion | D87: 240204176 | E87: 348674461 | F87: 120075884 | G87: =F87 -> 120075884 | H87: =G87 -> 120075884 | I87: =H87 -> 120075884 | J87: =I87 -> 120075884 | K87: =J87 -> 120075884
C88: Trades and notes payable | D88: 2161616663 | E88: 3430377678 | F88: 2792638925 | G88: =G210 -> 3.52864e+09 | H88: =H210 -> 3.7709994e+09 | I88: =I210 -> 4.0247248e+09 | J88: =J210 -> 4.2630013e+09 | K88: =K210 -> 4.5101434e+09
C89: Dividends payable | D89: 56816046 | E89: 170680629 | F89: 171431033 | G89: =F89 -> 171431033 | H89: =G89 -> 171431033 | I89: =H89 -> 171431033 | J89: =I89 -> 171431033 | K89: =J89 -> 171431033
C90: Creditors and other credit accounts | D90: 974651595 | E90: 1573371698 | F90: 1336918898 | G90: =G211 -> 1.4309188e+09 | H90: =H211 -> 1.5291994e+09 | I90: =I211 -> 1.632089e+09 | J90: =J211 -> 1.7287138e+09 | K90: =K211 -> 1.8289338e+09
C91: Tax payable | D91: 178656287 | E91: 310878862 | F91: 235085306 | G91: =G212 -> 2.5161436e+08 | H91: =H212 -> 2.6889612e+08 | I91: =I212 -> 2.8698834e+08 | J91: =J212 -> 3.0397896e+08 | K91: =K212 -> 3.2160176e+08
C92: Total Current Liabilities | D92: =SUM(D84:D91) -> 8142771728 | E92: =SUM(E84:E91) -> 13268943941 | F92: =SUM(F84:F91) -> 11693057903 | G92: =SUM(G84:G91) -> 1.2590198e+10 | H92: =SUM(H84:H91) -> 1.3001813e+10 | I92: =SUM(I84:I91) -> 1.3433465e+10 | J92: =SUM(J84:J91) -> 1.3843445e+10 | K92: =SUM(K84:K91) -> 1.4269523e+10
C94: Non-Current Liabilities
C95: Long term loans | D95: 246047654 | E95: 129447949 | F95: 109644343 | G95: =F95 -> 109644343 | H95: =G95 -> 109644343 | I95: =H95 -> 109644343 | J95: =I95 -> 109644343 | K95: =J95 -> 109644343
C96: Lease contracts liabilities | D96: 398927103 | E96: 464844105 | F96: 443662340 | G96: =G283*(1-G284) -> 5.2551789e+08 | H96: =H283*(1-H284) -> 6.1299557e+08 | I96: =I283*(1-I284) -> 7.0635903e+08 | J96: =J283*(1-J284) -> 8.0524992e+08 | K96: =K283*(1-K284) -> 9.0987387e+08
C97: Deferred tax liabilities | D97: 149355442 | E97: 0 | F97: 0 | G97: =F97 -> 0 | H97: =G97 -> 0 | I97: =H97 -> 0 | J97: =I97 -> 0 | K97: =J97 -> 0
C98: Total Non-Current Liabilities | D98: =SUM(D95:D97) -> 794330199 | E98: =SUM(E95:E97) -> 594292054 | F98: =SUM(F95:F97) -> 553306683 | G98: =SUM(G95:G97) -> 6.3516223e+08 | H98: =SUM(H95:H97) -> 7.2263991e+08 | I98: =SUM(I95:I97) -> 8.1600338e+08 | J98: =SUM(J95:J97) -> 9.1489426e+08 | K98: =SUM(K95:K97) -> 1.0195182e+09
C100: Total Liabilities | D100: =D92+D98 -> 8937101927 | E100: =E92+E98 -> 13863235995 | F100: =F92+F98 -> 12246364586 | G100: =G92+G98 -> 1.322536e+10 | H100: =H92+H98 -> 1.3724453e+10 | I100: =I92+I98 -> 1.4249469e+10 | J100: =J92+J98 -> 1.4758339e+10 | K100: =K92+K98 -> 1.5289041e+10
C102: Equity
C103: Issued and paid up capital | D103: 665107268 | E103: 665107268 | F103: 665107268 | G103: =F103 -> 665107268 | H103: =G103 -> 665107268 | I103: =H103 -> 665107268 | J103: =I103 -> 665107268 | K103: =J103 -> 665107268
C104: Reserves | D104: 1794626861 | E104: 1522976435 | F104: 1534111447 | G104: =F104 -> 1534111447 | H104: =G104 -> 1534111447 | I104: =H104 -> 1534111447 | J104: =I104 -> 1534111447 | K104: =J104 -> 1534111447
C105: Retained earnings | D105: 704841104 | E105: 1716117620 | F105: 2482016283 | G105: =G251 -> 5.3982476e+09 | H105: =H251 -> 6.1765644e+09 | I105: =I251 -> 7.0145914e+09 | J105: =J251 -> 7.909654e+09 | K105: =K251 -> 8.8648029e+09
C106: Net profit for the period / year | D106: 1740203598 | E106: 2192283305 | F106: 2189343558 | G106: 0 | H106: 0 | I106: 0 | J106: 0 | K106: 0
C107: Exchange differences on translation | D107: 7904577917 | E107: 12810841902 | F107: 11995255064 | G107: =F107 -> 11995255064 | H107: =G107 -> 11995255064 | I107: =H107 -> 11995255064 | J107: =I107 -> 11995255064 | K107: =J107 -> 11995255064
C108: Total equity attributable to parent | D108: =SUM(D103:D107) -> 12809356748 | E108: =SUM(E103:E107) -> 18907326530 | F108: =SUM(F103:F107) -> 18865833620 | G108: =SUM(G103:G107) -> 1.9592721e+10 | H108: =SUM(H103:H107) -> 2.0371038e+10 | I108: =SUM(I103:I107) -> 2.1209065e+10 | J108: =SUM(J103:J107) -> 2.2104128e+10 | K108: =SUM(K103:K107) -> 2.3059277e+10
C109: Non-controlling interest | D109: 1361533283 | E109: 2134004061 | F109: 1966368620 | G109: =G257 -> 1.9048548e+09 | H109: =H257 -> 1.8389887e+09 | I109: =I257 -> 1.7680696e+09 | J109: =J257 -> 1.6923237e+09 | K109: =K257 -> 1.611493e+09
C110: Total Equity | D110: =SUM(D108:D109) -> 14170890031 | E110: =SUM(E108:E109) -> 21041330591 | F110: =SUM(F108:F109) -> 20832202240 | G110: =SUM(G108:G109) -> 2.1497576e+10 | H110: =SUM(H108:H109) -> 2.2210027e+10 | I110: =SUM(I108:I109) -> 2.2977135e+10 | J110: =SUM(J108:J109) -> 2.3796452e+10 | K110: =SUM(K108:K109) -> 2.467077e+10
C112: Total Liabilites & Equity | D112: =D100+D110 -> 23107991958 | E112: =E100+E110 -> 34904566586 | F112: =F100+F110 -> 33078566826 | G112: =G100+G110 -> 3.4722936e+10 | H112: =H100+H110 -> 3.593448e+10 | I112: =I100+I110 -> 3.7226603e+10 | J112: =J100+J110 -> 3.8554791e+10 | K112: =K100+K110 -> 3.9959811e+10
C114: Balance Check | D114: =D79-D112 -> 0 | E114: =E79-E112 -> 0 | F114: =F79-F112 -> 0 | G114: =G79-G112 -> 0 | H114: =H79-H112 -> 0 | I114: =I79-I112 -> 0 | J114: =J79-J112 -> 0 | K114: =K79-K112 -> 0
C116: CASH FLOW STATEMENT
C117: Fiscal year | G117: =G$13 -> 2026 | H117: =H$13 -> 2027 | I117: =I$13 -> 2028 | J117: =J$13 -> 2029 | K117: =K$13 -> 2030
C118: Fiscal year end date | G118: =G$14 -> 46387 | H118: =H$14 -> 46752 | I118: =I$14 -> 47118 | J118: =J$14 -> 47483 | K118: =K$14 -> 47848
...

Sheet DCF
B2: Discounted Cash Flow Valuation
B3: =FSM!C3 -> All amounts are shown in EGP, except per-share data, ratios, and shares outstanding
B4: Most recent fiscal year end | D4: 46022 | F4: Discount rate (WACC) | H4: =+WACC!E21 -> 0.19536055 | I4: Link from WACC
B5: End of first fiscal year | D5: =EOMONTH(D4,12) -> 46387 | F5: Share price (Public Co) | H5: 23.48
B6: Most recent quarter end date | D6: 46022 | F6: Share price date | H6: 46188
B7: Valuation date | D7: 46190 | F7: Implied Share Price | H7: =C73 -> 29.428047
B8: Portion of First Year Cash Flows | D8: =YEARFRAC(D7,D5) -> 0.53888889 | F8: Upside / (Downside) | H8: =H7/H5-1 -> 0.25332397
F9: Midyear adjustment? | H9: 1
B10: Unlevered Free Cash Flows
C11: LTM | D11: Actual | E11: Forecasts
B12: Fiscal year ended | C12: =D7 -> 46190 | D12: =D4 -> 46022 | E12: =EOMONTH(D12,12) -> 46387 | F12: =EOMONTH(E12,12) -> 46752 | G12: =EOMONTH(F12,12) -> 47118 | H12: =EOMONTH(G12,12) -> 47483 | I12: =EOMONTH(H12,12) -> 47848
B14: Revenue | C14: =E14*(1-$D$8)+D14*$D$8 -> 2.7485939e+10 | D14: =FSM!F16 -> 26622797999 | E14: =FSM!G16 -> 28494670000 | F14: =FSM!H16 -> 3.0451784e+10 | G14: =FSM!I16 -> 3.2500681e+10 | H14: =FSM!J16 -> 3.4424825e+10 | I14: =FSM!K16 -> 3.6420561e+10
B15: % growth | E15: =E14/D14-1 -> 0.070310867 | F15: =F14/E14-1 -> 0.068683517 | G15: =G14/F14-1 -> 0.067283326 | H15: =H14/G14-1 -> 0.059203183 | I15: =I14/H14-1 -> 0.057973733
B16: EBITDA | C16: =E16*(1-$D$8)+D16*$D$8 -> 3.8743606e+09 | D16: =FSM!F42 -> 3667611139 | E16: =FSM!G42 -> 4.1159835e+09 | F16: =FSM!H42 -> 4.3986837e+09 | G16: =FSM!I42 -> 4.6946418e+09 | H16: =FSM!J42 -> 4.9725796e+09 | I16: =FSM!K42 -> 5.2608586e+09
B17: % margin | D17: =D16/D14 -> 0.13776205 | E17: =E16/E14 -> 0.14444749 | F17: =F16/F14 -> 0.14444749 | G17: =G16/G14 -> 0.14444749 | H17: =H16/H14 -> 0.14444749 | I17: =I16/I14 -> 0.14444749
B18: EBIT | C18: =E18*(1-$D$8)+D18*$D$8 -> 2.5554543e+09 | D18: =FSM!F28 -> 2390730054 | E18: =FSM!G28 -> 2.7479634e+09 | F18: =FSM!H28 -> 2.9367032e+09 | G18: =FSM!I28 -> 3.1342944e+09 | H18: =FSM!J28 -> 3.3198546e+09 | I18: =FSM!K28 -> 3.512319e+09
B19: % margin | D19: =D18/D14 -> 0.089800105 | E19: =E18/E14 -> 0.096437806 | F19: =F18/F14 -> 0.096437806 | G19: =G18/G14 -> 0.096437806 | H19: =H18/H14 -> 0.096437806 | I19: =I18/I14 -> 0.096437806
B21: Tax on EBIT | D21: =D18*D22 -> 3.398535e+08 | E21: =E18*E22 -> 3.0104209e+08 | F21: =F18*F22 -> 3.2171872e+08 | G21: =G18*G22 -> 3.4336503e+08 | H21: =H18*H22 -> 3.6369333e+08 | I21: =I18*I22 -> 3.8477799e+08
B22: Tax rate | D22: =-FSM!F53 -> 0.1421547 | E22: =-FSM!G53 -> 0.10955098 | F22: =-FSM!H53 -> 0.10955098 | G22: =-FSM!I53 -> 0.10955098 | H22: =-FSM!J53 -> 0.10955098 | I22: =-FSM!K53 -> 0.10955098
B23: NOPAT (aka EBIAT) | D23: =D18*(1-D22) -> 2.0508765e+09 | E23: =E18*(1-E22) -> 2.4469214e+09 | F23: =F18*(1-F22) -> 2.6149845e+09 | G23: =G18*(1-G22) -> 2.7909294e+09 | H23: =H18*(1-H22) -> 2.9561613e+09 | I23: =I18*(1-I22) -> 3.127541e+09
B25: Depreciation & amortization | E25: =FSM!G164 -> 1.3680201e+09 | F25: =FSM!H164 -> 1.4619805e+09 | G25: =FSM!I164 -> 1.5603474e+09 | H25: =FSM!J164 -> 1.6527249e+09 | I25: =FSM!K164 -> 1.7485396e+09
B26: Changes in net working capital | E26: =D32-E32 -> -1.737846e+09 | F26: =E32-F32 -> -9.06011e+08 | G26: =F32-G32 -> -9.4850037e+08 | H26: =G32-H32 -> -8.9074796e+08 | I26: =H32-I32 -> -9.2389012e+08
B27: Capital expenditures | E27: =-FSM!G153 -> -1.0429717e+09 | F27: =-FSM!H153 -> -1.1146067e+09 | G27: =-FSM!I153 -> -1.1896012e+09 | H27: =-FSM!J153 -> -1.2600293e+09 | I27: =-FSM!K153 -> -1.3330779e+09
B28: as % of revenue | E28: =E27/E14 -> -0.036602345 | F28: =F27/F14 -> -0.036602345 | G28: =G27/G14 -> -0.036602345 | H28: =H27/H14 -> -0.036602345 | I28: =I27/I14 -> -0.036602345
B30: Unlevered free cash flows (UFCF) | E30: =E23+E25+E26+E27 -> 1.0341237e+09 | F30: =F23+F25+F26+F27 -> 2.0563473e+09 | G30: =G23+G25+G26+G27 -> 2.2131753e+09 | H30: =H23+H25+H26+H27 -> 2.4581089e+09 | I30: =I23+I25+I26+I27 -> 2.6191125e+09
B32: Net working capital (WC Assets - WC liabilities) | D32: =FSM!F215 -> 11453251931 | E32: =FSM!G215 -> 1.3191098e+10 | F32: =FSM!H215 -> 1.4097109e+10 | G32: =FSM!I215 -> 1.5045609e+10 | H32: =FSM!J215 -> 1.5936357e+10 | I32: =FSM!K215 -> 1.6860247e+10
B33: as % of revenue | D33: =D32/D14 -> 0.43020467 | E33: =E32/E14 -> 0.46293212 | F33: =F32/F14 -> 0.46293212 | G33: =G32/G14 -> 0.46293212 | H33: =H32/H14 -> 0.46293212 | I33: =I32/I14 -> 0.46293212
B35: ="Present value of UFCF on "&TEXT(D7,"mmm dd, yyyy")&" valuation date" -> Present value of UFCF on Jun 17, 2026 valuation date
D36: Val date | E36: Yr 1 - Stub | F36: Year 2 | G36: Year 3 | H36: Year 4 | I36: Year 5
B37: Date for discounting cash flows | D37: =D7 -> 46190 | E37: =IF($H$9=1,AVERAGE(E12,D37),E12) -> 46288.5 | F37: =IF($H$9=1,AVERAGE(F12,E12),F12) -> 46569.5 | G37: =IF($H$9=1,AVERAGE(G12,F12),G12) -> 46935 | H37: =IF($H$9=1,AVERAGE(H12,G12),H12) -> 47300.5 | I37: =IF($H$9=1,AVERAGE(I12,H12),I12) -> 47665.5
B38: Unlevered free cash flows (UFCF) stub adjusted | C38: =D8 -> 0.53888889 | E38: =E30*C38 -> 5.5727779e+08 | F38: =F30 -> 2.0563473e+09 | G38: =G30 -> 2.2131753e+09 | H38: =H30 -> 2.4581089e+09 | I38: =I30 -> 2.6191125e+09
B39: Present value of of unlevered free cash flows | E39: =E38/(1+$H$4)^((E37-$D$37)/365) -> 5.3107718e+08 | F39: =F38/(1+$H$4)^((F37-$D$37)/365) -> 1.7081218e+09 | G39: =G38/(1+$H$4)^((G37-$D$37)/365) -> 1.5375636e+09 | H39: =H38/(1+$H$4)^((H37-$D$37)/365) -> 1.4282799e+09 | I39: =I38/(1+$H$4)^((I37-$D$37)/365) -> 1.2731144e+09
B41: Terminal value - growth in perpetuity approach | E41: Terminal value - EBITDA multiple approach
B42: Long term growth rate | C42: 0.1 | E42: Terminal year EBITDA | I42: =I16 -> 5.2608586e+09
B43: =YEAR(I12)&" FCF x (1+g)" -> 2030 FCF x (1+g) | C43: =I38*(1+C42) -> 2.8810238e+09 | E43: EBITDA multiple | I43: 5.9
B44: ="Terminal value in "&YEAR(I12) -> Terminal value in 2030 | C44: =C43/(H4-C42) -> 3.0211904e+10 | E44: ="Terminal value in "&YEAR(I12) -> Terminal value in 2030 | I44: =I42*I43 -> 3.1039065e+10
B45: Present value of terminal value | C45: =C44/(1+H4)^((I37-$D$37)/365) -> 1.4685589e+10 | E45: Present value of terminal value | I45: =I44/(1+H4)^((I37-D37)/365) -> 1.5087661e+10
B46: Present value of stage 1 cash flows | C46: =SUM(E39:I39) -> 6.4781568e+09 | E46: Present value of stage 1 cash flows | I46: =C46 -> 6.4781568e+09
B47: Total enterprise value (TEV) | C47: =C45+C46 -> 2.1163746e+10 | E47: Enterprise value (stage 1 + 2) | I47: =I45+I46 -> 2.1565818e+10
B49: Terminal value as % of TEV | C49: =C45/C47 -> 0.69390311 | E49: Terminal value as % of TEV | I49: =I45/I47 -> 0.69960996
B50: Stage 1 cash flows as % of TEV | C50: =1-C49 -> 0.30609689 | E50: Cash flows as % of TEV | I50: =1-I49 -> 0.30039004
B51: Implied TV exit EBITDA multiple | C51: =C44/I16 -> 5.7427706 | E51: Implied terminal growth rate | I51: =(H4-I38/I44)/(1+I38/I44) -> 0.10234352
B53: Net debt | E53: Shares outstanding
B54: Source doc | C54: Consolidated FS 2025
B55: Source date | C55: 12/31/2025 | G55: Source doc | H55: Date | I55: Shares
B56: Gross debt and equivalents | E56: Basic shares | G56: Consolidated FS 2025 | H56: 12/31/2025 | I56: 665107268
B57: Debt | C57: =FSM!F85+FSM!F86+FSM!F87+FSM!F95+FSM!F96 -> 7469154055 | E57: Restricted stock / RSUs
B58: Convertible debt | E58: Options / warrants
B59: Preferred stock | E59: Convertible debt
B60: Noncontrolling (minority) interests | C60: =FSM!F109 -> 1966368620 | E60: Convertible preferred stock
B61: Nonoperating assets | E61: Net diluted shares outstanding | I61: =SUM(I56:I60) -> 665107268
B62: Cash | C62: =FSM!F68 -> 4632540191
B63: Equity investments | C63: =FSM!F76 -> 1010593966
B64: Debt securities (optional cash asset) | C64: =FSM!F65+FSM!F66+FSM!F67 -> 2201450659
B65: Net debt | C65: =SUM(C57:C60)-SUM(C62:C64) -> 1590937859
B67: Valuation
C68: Perpetuity | D68: EBITDA
B69: Enterprise value | C69: =C47 -> 2.1163746e+10 | D69: =I47 -> 2.1565818e+10
B70: Net debt | C70: =C65 -> 1590937859 | D70: =C65 -> 1590937859
B71: Equity value | C71: =C69-C70 -> 1.9572808e+10 | D71: =D69-D70 -> 1.997488e+10
B72: Shares outstanding | C72: =$I$61 -> 665107268 | D72: =$I$61 -> 665107268
B73: Equity value per share | C73: =C71/C72 -> 29.428047 | D73: =D71/D72 -> 30.032569
C75: Last twelve months (LTM)
C76: Perpetuity | D76: EBITDA
B77: EV / Revenue | C77: =C69/$C$14 -> 0.76998445 | D77: =D69/$C$14 -> 0.78461273
B78: EV / EBITDA | C78: =C69/$C$16 -> 5.4625131 | D78: =D69/$C$16 -> 5.5662907
B79: EV / EBIT | C79: =C69/$C$18 -> 8.2817937 | D79: =D69/$C$18 -> 8.4391324
C80: Year 1
C81: Perpetuity | D81: EBITDA
B82: EV / Revenue | C82: =C69/$E$14 -> 0.74272647 | D82: =D69/$E$14 -> 0.7568369
B83: EV / EBITDA | C83: =C69/$E$16 -> 5.1418441 | D83: =D69/$E$16 -> 5.2395296
B84: EV / EBIT | C84: =C69/$E$18 -> 7.7016111 | D84: =D69/$E$18 -> 7.8479274
B86: Outputs
D88: Equity value per share | L88: LTM EBITDA multiple
E89: Long term growth rate (g): | L89: Long term growth rate (g):
D90: =C73 -> 29.428047 | E90: =F90-0.005 -> 0.09 | F90: =G90-0.005 -> 0.095 | G90: =$C$42 -> 0.1 | H90: =G90+0.005 -> 0.105 | I90: =H90+0.005 -> 0.11 | L90: =C78 -> 5.4625131 | M90: =N90-0.005 -> 0.09 | N90: =O90-0.005 -> 0.095 | O90: =$C$42 -> 0.1 | P90: =O90+0.005 -> 0.105 | Q90: =P90+0.005 -> 0.11
D91: =D92+0.01 -> 0.21536055 | E91: 22.557252 | F91: 21.891652 | G91: 21.891652 | H91: 22.557252 | I91: 24.061542 | L91: =L92+0.01 -> 0.21536055 | M91: 4.2830112 | N91: 4.1687484 | O91: 4.1687484 | P91: 4.2830112 | Q91: 4.5412511
D92: =D93+0.01 -> 0.20536055 | E92: 24.655112 | F92: 23.851779 | G92: 23.851779 | H92: 24.655112 | I92: 26.490515 | L92: =L93+0.01 -> 0.20536055 | M92: 4.6431485 | N92: 4.5052413 | O92: 4.5052413 | P92: 4.6431485 | Q92: 4.9582302
C93: WACC: | D93: =WACC!$E$21 -> 0.19536055 | E93: 27.150707 | F93: 26.166803 | G93: 26.166803 | H93: 27.150707 | I93: 29.428047 | K93: WACC: | L93: =WACC!$E$21 -> 0.19536055 | M93: 5.0715646 | N93: 4.9026589 | O93: 4.9026589 | P93: 5.0715646 | Q93: 5.4625131
D94: =D93-0.01 -> 0.18536055 | E94: 30.169146 | F94: 28.942799 | G94: 28.942799 | H94: 30.169146 | I94: 33.052839 | L94: =L93-0.01 -> 0.18536055 | M94: 5.5897368 | N94: 5.3792112 | O94: 5.3792112 | P94: 5.5897368 | Q94: 6.0847771
B95: Data | D95: =D94-0.01 -> 0.17536055 | E95: 33.894162 | F95: 32.332802 | G95: 32.332802 | H95: 33.894162 | I95: 37.638439 | L95: =L94-0.01 -> 0.17536055 | M95: 6.2292063 | N95: 5.9611692 | O95: 5.9611692 | P95: 6.2292063 | Q95: 6.8719822
B96: Tables
D97: Equity value per share | L97: LTM EBITDA multiple
E98: Exit EBITDA Multiple | M98: Exit EBITDA Multiple
D99: =D73 -> 30.032569 | E99: =+F99-0.5 -> 4.9 | F99: =+G99-0.5 -> 5.4 | G99: =$I$43 -> 5.9 | H99: =+G99+0.5 -> 6.4 | I99: =+H99+0.5 -> 6.9 | L99: =D78 -> 5.5662907 | M99: =+N99-0.5 -> 4.9 | N99: =+O99-0.5 -> 5.4 | O99: =$I$43 -> 5.9 | P99: =+O99+0.5 -> 6.4 | Q99: =+P99+0.5 -> 6.9
D100: =D101+0.01 -> 0.21536055 | E100: 24.611102 | F100: 22.813401 | G100: 22.813401 | H100: 24.611102 | I100: 28.206502 | L100: =L101+0.01 -> 0.21536055 | M100: 4.6355934 | N100: 4.3269841 | O100: 4.3269841 | P100: 4.6355934 | Q100: 5.2528119
D101: =D102+0.01 -> 0.20536055 | E101: 25.383768 | F101: 23.525012 | G101: 23.525012 | H101: 25.383768 | I101: 29.10128 | L101: =L102+0.01 -> 0.20536055 | M101: 4.7682362 | N101: 4.4491456 | O101: 4.4491456 | P101: 4.7682362 | Q101: 5.4064174
C102: WACC: | D102: =WACC!$E$21 -> 0.19536055 | E102: 26.187729 | F102: 24.26531 | G102: 24.26531 | H102: 26.187729 | I102: 30.032569 | K102: WACC: | L102: =WACC!$E$21 -> 0.19536055 | M102: 4.9062513 | N102: 4.5762316 | O102: 4.5762316 | P102: 4.9062513 | Q102: 5.5662907
D103: =D102-0.01 -> 0.18536055 | E103: 27.024558 | F103: 25.035731 | G103: 25.035731 | H103: 27.024558 | I103: 31.002211 | L103: =L102-0.01 -> 0.18536055 | M103: 5.0499088 | N103: 4.7084891 | O103: 4.7084891 | P103: 5.0499088 | Q103: 5.7327482
D104: =D103-0.01 -> 0.17536055 | E104: 27.895921 | F104: 25.837801 | G104: 25.837801 | H104: 27.895921 | I104: 32.01216 | L104: =L103-0.01 -> 0.17536055 | M104: 5.1994947 | N104: 4.8461796 | O104: 4.8461796 | P104: 5.1994947 | Q104: 5.9061251
B106: Equity value range | G106: Football field
C127: Low | D127: Diff. | E127: High | O127: Low | P127: Diff. | Q127: High
B128: ="DCF Value at "&TEXT(E99,"0.0x")&"-"&TEXT(I99,"0.0x")&" Exit EBITDA Range at "&TEXT(D102,"0.0%")&" WACC" -> DCF Value at 4.9x-6.9x Exit EBITDA Range at 19.5% WACC | C128: =E102 -> 26.187729 | D128: =E128-C128 -> 3.8448394 | E128: =I102 -> 30.032569 | G128: ="LTM EBITDA Purchase Multiple at "&TEXT(M90,"0.0%")&"-"&TEXT(Q90,"0.0%")&" Perpetuity Growth at "&TEXT(L93,"0.0%")&" WACC" -> LTM EBITDA Purchase Multiple at 9.0%-11.0% Perpetuity Growth at 19.5% WACC | O128: =M93 -> 5.0715646 | P128: =Q128-O128 -> 0.39094848 | Q128: =Q93 -> 5.4625131
B129: ="DCF Value at "&TEXT(E90,"0.0%")&"-"&TEXT(I90,"0.0%")&" Perpetuity Range at "&TEXT(D102,"0.0%")&" WACC" -> DCF Value at 9.0%-11.0% Perpetuity Range at 19.5% WACC | C129: =E93 -> 27.150707 | D129: =E129-C129 -> 2.27734 | E129: =I93 -> 29.428047 | G129: ="LTM EBITDA Purchase Multiple at "&TEXT(M102,"0.0x")&"-"&TEXT(Q102,"0.0x")&" Exit EBITDA Multiple at "&TEXT(L102,"0.0%")&" WACC" -> LTM EBITDA Purchase Multiple at 4.9x-5.6x Exit EBITDA Multiple at 19.5% WACC | O129: =M102 -> 4.9062513 | P129: =Q129-O129 -> 0.66003939 | Q129: =Q102 -> 5.5662907
B130: 52 Week Market High/Low | C130: 20.3 | D130: =E130-C130 -> 4.81 | E130: 25.11 | G130: ="LTM EBITDA Purchase Multiple at "&TEXT(L104,"0.0%")&"-"&TEXT(L100,"0.0%")&" WACC at "&TEXT(O99,"0.0x")&" Exit EBITDA" -> LTM EBITDA Purchase Multiple at 17.5%-21.5% WACC at 5.9x Exit EBITDA | O130: =O100 -> 4.3269841 | P130: =Q130-O130 -> 0.51919548 | Q130: =O104 -> 4.8461796

Sheet WACC
B2: WACC Buildup
B3: =DCF!B3 -> All amounts are shown in EGP, except per-share data, ratios, and shares outstanding
B4: Cost of capital assumptions
B6: Cost of debt | C6: =C10+2% -> 0.215826
B7: Tax rate | C7: 0.225
B8: Cost of debt (after tax) | C8: =C6*(1-C7) -> 0.16726515
B10: Risk free rate | C10: 0.195826
B11: Beta | C11: =(2/3*-0.04)+1/3 -> 0.30666667
B12: Market risk premium | C12: =13.94%-9.71% -> 0.0423
B13: Cost of equity | C13: =C10+C11*C12 -> 0.208798
B15: Capital weights (capital structure)
D16: Target
C17: Current | D17: (override) | E17: % of total
B18: Equity | C18: =DCF!H5*DCF!I61 -> 1.5616719e+10 | E18: =C18/(C18+C19) -> 0.67646213
B19: Debt | C19: =DCF!C57 -> 7469154055 | E19: =C19/(C18+C19) -> 0.32353787
B21: Cost of capital (WACC) | E21: =C13*E18+C8*E19 -> 0.19536055
